[{"count": 1, "pub_date": "2014-07-06T00:00:00Z"}, {"count": 1, "pub_date": "2014-11-11T11:45:31Z"}, {"count": 1, "pub_date": "2016-12-23T15:58:32+0000"}, {"count": 1, "pub_date": "2017-02-14T19:34:44+0000"}, {"count": 1, "pub_date": "2016-10-26T00:22:26+0000"}, {"count": 2, "pub_date": "2016-10-23T22:46:56+0000"}, {"count": 1, "pub_date": "2016-12-06T03:04:09+0000"}, {"count": 2, "pub_date": "2016-04-07T00:00:00Z"}, {"count": 1, "pub_date": "2016-10-16T04:00:00+0000"}, {"count": 1, "pub_date": "2014-09-15T13:30:22Z"}, {"count": 1, "pub_date": "2016-07-08T00:00:00Z"}, {"count": 1, "pub_date": "2015-04-27T07:57:50Z"}, {"count": 1, "pub_date": "2016-09-10T00:05:09+0000"}, {"count": 1, "pub_date": "2015-10-04T05:30:59Z"}, {"count": 1, "pub_date": "2015-08-17T00:00:00Z"}, {"count": 1, "pub_date": "2014-09-18T21:19:23Z"}, {"count": 1, "pub_date": "2014-08-29T06:52:42Z"}, {"count": 1, "pub_date": "2015-04-08T08:10:07Z"}, {"count": 1, "pub_date": "2016-04-06T17:54:49Z"}, {"count": 2, "pub_date": "2015-07-10T00:00:00Z"}, {"count": 1, "pub_date": "2014-09-01T00:00:00Z"}, {"count": 1, "pub_date": "2015-02-20T00:00:00Z"}, {"count": 1, "pub_date": "2017-02-07T17:02:37+0000"}, {"count": 1, "pub_date": "2014-06-01T11:00:46Z"}, {"count": 1, "pub_date": "2016-04-08T00:00:00Z"}, {"count": 1, "pub_date": "2016-03-14T06:06:12Z"}, {"count": 2, "pub_date": "2016-03-04T00:00:00Z"}, {"count": 1, "pub_date": "2015-09-08T00:00:00Z"}, {"count": 2, "pub_date": "2016-06-16T00:00:00Z"}, {"count": 1, "pub_date": "2015-09-02T07:46:58Z"}, {"count": 1, "pub_date": "2017-01-27T16:50:24+0000"}, {"count": 1, "pub_date": "2014-08-04T00:00:00Z"}, {"count": 2, "pub_date": "2016-12-13T10:00:05+0000"}, {"count": 2, "pub_date": "2016-08-05T04:00:00+0000"}, {"count": 1, "pub_date": "2016-06-01T00:00:00Z"}, {"count": 1, "pub_date": "2016-11-15T23:08:05Z"}, {"count": 1, "pub_date": "2015-11-26T00:00:00Z"}, {"count": 1, "pub_date": "2015-01-14T14:51:17Z"}, {"count": 1, "pub_date": "2015-07-01T00:00:00Z"}, {"count": 1, "pub_date": "2015-06-08T16:26:51Z"}, {"count": 2, "pub_date": "2015-09-07T00:00:00Z"}, {"count": 2, "pub_date": "2015-05-07T00:00:00Z"}, {"count": 2, "pub_date": "2016-07-12T00:00:00Z"}, {"count": 1, "pub_date": "2016-03-15T00:00:00Z"}, {"count": 1, "pub_date": "2016-06-17T17:57:14+0000"}, {"count": 1, "pub_date": "2015-11-12T11:00:56Z"}, {"count": 1, "pub_date": "2015-09-16T11:47:55Z"}, {"count": 1, "pub_date": "2015-04-30T00:00:00Z"}, {"count": 2, "pub_date": "2015-06-06T00:00:00Z"}, {"count": 1, "pub_date": "2015-11-01T00:00:00Z"}, {"count": 2, "pub_date": "2014-09-15T00:00:00Z"}, {"count": 1, "pub_date": "2017-01-31T02:07:42+0000"}, {"count": 4, "pub_date": "2016-02-26T00:00:00Z"}, {"count": 2, "pub_date": "2016-08-17T04:00:00+0000"}, {"count": 4, "pub_date": "2015-01-22T00:00:00Z"}, {"count": 1, "pub_date": "2014-05-29T02:10:43Z"}, {"count": 2, "pub_date": "2015-02-12T20:13:03Z"}, {"count": 1, "pub_date": "2016-04-15T00:00:00Z"}, {"count": 1, "pub_date": "2015-04-27T00:00:00Z"}, {"count": 2, "pub_date": "2015-12-31T00:00:00Z"}, {"count": 2, "pub_date": "2015-07-20T00:00:00Z"}, {"count": 1, "pub_date": "2015-10-28T09:23:14Z"}, {"count": 1, "pub_date": "2016-05-01T00:00:00Z"}, {"count": 1, "pub_date": "2017-01-23T10:42:07+0000"}, {"count": 1, "pub_date": "2014-09-17T23:11:55Z"}, {"count": 1, "pub_date": "2016-01-14T00:00:00Z"}, {"count": 1, "pub_date": "2016-03-27T00:00:00Z"}, {"count": 1, "pub_date": "2015-07-24T09:25:14Z"}, {"count": 1, "pub_date": "2016-02-04T00:00:00Z"}, {"count": 1, "pub_date": "2016-07-01T05:51:46Z"}, {"count": 4, "pub_date": "2016-03-29T00:00:00Z"}, {"count": 1, "pub_date": "2015-12-04T18:37:36Z"}, {"count": 1, "pub_date": "2014-12-10T08:30:08Z"}, {"count": 1, "pub_date": "2016-02-18T05:57:30Z"}, {"count": 1, "pub_date": "2017-01-05T16:48:35+0000"}, {"count": 1, "pub_date": "2015-06-23T00:00:00Z"}, {"count": 2, "pub_date": "2016-07-22T00:00:00Z"}, {"count": 1, "pub_date": "2015-05-28T15:48:24Z"}, {"count": 1, "pub_date": "2017-02-06T10:46:43+0000"}, {"count": 1, "pub_date": "2016-12-15T01:15:43+0000"}, {"count": 1, "pub_date": "2014-11-06T20:46:56Z"}, {"count": 3, "pub_date": "2015-03-18T00:00:00Z"}, {"count": 1, "pub_date": "2015-09-30T09:00:17Z"}, {"count": 3, "pub_date": "2016-03-07T00:00:00Z"}, {"count": 1, "pub_date": "2016-12-08T17:13:44+0000"}, {"count": 1, "pub_date": "2017-02-08T17:00:52+0000"}, {"count": 1, "pub_date": "2015-08-26T12:15:55Z"}, {"count": 1, "pub_date": "2015-11-28T00:00:00Z"}, {"count": 1, "pub_date": "2016-03-11T00:00:00Z"}, {"count": 1, "pub_date": "2016-10-10T04:00:00+0000"}, {"count": 1, "pub_date": "2015-04-17T12:30:48Z"}, {"count": 1, "pub_date": "2016-08-22T04:00:00+0000"}, {"count": 1, "pub_date": "2015-04-24T00:00:00Z"}, {"count": 3, "pub_date": "2015-03-02T00:00:00Z"}, {"count": 1, "pub_date": "2016-04-27T15:15:27Z"}, {"count": 3, "pub_date": "2016-09-12T04:00:00+0000"}, {"count": 1, "pub_date": "2016-12-23T01:14:44+0000"}, {"count": 1, "pub_date": "2016-11-30T11:00:57+0000"}, {"count": 1, "pub_date": "2015-06-20T00:00:00Z"}, {"count": 1, "pub_date": "2016-12-14T16:30:01+0000"}, {"count": 1, "pub_date": "2015-06-08T09:11:06Z"}, {"count": 1, "pub_date": "2016-01-28T06:09:25Z"}, {"count": 1, "pub_date": "2016-12-13T16:54:29+0000"}, {"count": 1, "pub_date": "2017-02-11T14:00:04+0000"}, {"count": 1, "pub_date": "2016-03-14T11:08:53Z"}, {"count": 1, "pub_date": "2015-10-27T05:41:48Z"}, {"count": 1, "pub_date": "2016-10-24T23:59:25+0000"}, {"count": 2, "pub_date": "2016-01-26T00:00:00Z"}, {"count": 1, "pub_date": "2016-02-01T09:26:12Z"}, {"count": 1, "pub_date": "2014-08-25T06:37:21Z"}, {"count": 2, "pub_date": "2015-11-11T00:00:00Z"}, {"count": 6, "pub_date": "2016-03-03T00:00:00Z"}, {"count": 2, "pub_date": "2014-10-15T09:10:06Z"}, {"count": 1, "pub_date": "2015-06-09T11:30:25Z"}, {"count": 1, "pub_date": "2015-12-17T00:00:00Z"}, {"count": 2, "pub_date": "2016-01-27T00:00:00Z"}, {"count": 1, "pub_date": "2015-05-15T00:00:00Z"}, {"count": 1, "pub_date": "2015-04-30T20:38:52Z"}, {"count": 1, "pub_date": "2016-10-27T23:15:31+0000"}, {"count": 1, "pub_date": "2016-04-25T00:00:00Z"}, {"count": 2, "pub_date": "2014-10-01T00:00:00Z"}, {"count": 1, "pub_date": "2016-12-12T00:41:07+0000"}, {"count": 4, "pub_date": "2014-06-16T00:00:00Z"}, {"count": 1, "pub_date": "2014-06-02T00:00:00Z"}, {"count": 2, "pub_date": "2014-12-01T00:00:00Z"}, {"count": 1, "pub_date": "2017-01-05T19:24:58+0000"}, {"count": 1, "pub_date": "2017-02-22T16:49:28+0000"}, {"count": 1, "pub_date": "2017-01-06T17:54:56+0000"}, {"count": 1, "pub_date": "2016-12-14T12:21:07+0000"}, {"count": 1, "pub_date": "2017-01-13T17:49:43+0000"}, {"count": 1, "pub_date": "2016-03-22T04:00:00Z"}, {"count": 1, "pub_date": "2016-07-07T00:00:00Z"}, {"count": 1, "pub_date": "2015-09-14T00:00:00Z"}, {"count": 2, "pub_date": "2014-10-22T00:00:00Z"}, {"count": 2, "pub_date": "2014-09-30T00:00:00Z"}, {"count": 3, "pub_date": "2016-03-08T00:00:00Z"}, {"count": 1, "pub_date": "2016-10-18T16:04:31+0000"}, {"count": 1, "pub_date": "2016-03-04T10:28:41Z"}, {"count": 1, "pub_date": "2015-04-16T15:59:40Z"}, {"count": 1, "pub_date": "2016-11-20T21:56:49Z"}, {"count": 1, "pub_date": "2016-06-10T23:17:11Z"}, {"count": 1, "pub_date": "2016-03-22T06:20:38Z"}, {"count": 1, "pub_date": "2016-10-05T04:00:00+0000"}, {"count": 1, "pub_date": "2014-08-11T06:53:42Z"}, {"count": 1, "pub_date": "2016-03-18T06:03:08Z"}, {"count": 2, "pub_date": "2016-08-08T04:00:00+0000"}, {"count": 1, "pub_date": "2014-10-16T06:00:15Z"}, {"count": 1, "pub_date": "2014-12-17T00:00:00Z"}, {"count": 1, "pub_date": "2016-12-13T18:06:48+0000"}, {"count": 1, "pub_date": "2016-05-29T00:00:00Z"}, {"count": 1, "pub_date": "2016-03-23T06:09:10Z"}, {"count": 1, "pub_date": "2014-11-22T00:00:00Z"}, {"count": 1, "pub_date": "2016-05-27T06:34:12Z"}, {"count": 1, "pub_date": "2016-01-15T00:00:00Z"}, {"count": 1, "pub_date": "2016-02-28T00:00:00Z"}, {"count": 1, "pub_date": "2016-11-14T13:00:05Z"}, {"count": 2, "pub_date": "2015-06-08T00:00:00Z"}, {"count": 1, "pub_date": "2015-04-27T18:41:28Z"}, {"count": 2, "pub_date": "2015-12-18T00:00:00Z"}, {"count": 1, "pub_date": "2014-12-02T16:34:50Z"}, {"count": 1, "pub_date": "2014-11-17T08:49:43Z"}, {"count": 3, "pub_date": "2015-06-04T00:00:00Z"}, {"count": 1, "pub_date": "2014-10-27T06:24:05Z"}, {"count": 1, "pub_date": "2016-06-11T00:00:00Z"}, {"count": 1, "pub_date": "2015-03-09T00:00:00Z"}, {"count": 1, "pub_date": "2016-11-22T03:27:02Z"}, {"count": 1, "pub_date": "2017-01-01T23:00:24+0000"}, {"count": 1, "pub_date": "2016-01-01T00:00:00Z"}, {"count": 2, "pub_date": "2016-03-16T00:00:00Z"}, {"count": 1, "pub_date": "2015-04-08T20:32:52Z"}, {"count": 2, "pub_date": "2016-04-13T00:00:00Z"}, {"count": 1, "pub_date": "2015-05-05T08:01:45Z"}, {"count": 1, "pub_date": "2015-04-24T14:33:20Z"}, {"count": 3, "pub_date": "2015-06-11T00:00:00Z"}, {"count": 1, "pub_date": "2017-01-18T00:11:21+0000"}, {"count": 1, "pub_date": "2015-12-15T06:12:09Z"}, {"count": 1, "pub_date": "2016-03-03T05:51:08Z"}, {"count": 2, "pub_date": "2016-06-28T00:00:00Z"}, {"count": 1, "pub_date": "2015-05-19T00:00:00Z"}, {"count": 1, "pub_date": "2014-07-16T06:32:16Z"}, {"count": 1, "pub_date": "2014-09-09T17:13:59Z"}, {"count": 2, "pub_date": "2016-02-06T00:00:00Z"}, {"count": 1, "pub_date": "2015-04-28T00:00:00Z"}, {"count": 1, "pub_date": "2015-09-30T00:00:00Z"}, {"count": 1, "pub_date": "2016-01-12T00:00:00Z"}, {"count": 1, "pub_date": "2017-01-30T02:00:03+0000"}, {"count": 1, "pub_date": "2015-04-30T12:30:00Z"}, {"count": 1, "pub_date": "2014-08-29T15:31:28Z"}, {"count": 1, "pub_date": "2016-07-02T00:00:00Z"}, {"count": 1, "pub_date": "2014-10-01T06:59:16Z"}, {"count": 1, "pub_date": "2015-04-08T17:32:48Z"}, {"count": 1, "pub_date": "2015-08-05T00:00:00Z"}, {"count": 1, "pub_date": "2014-08-04T16:27:48Z"}, {"count": 2, "pub_date": "2016-09-29T04:00:00+0000"}, {"count": 1, "pub_date": "2016-09-15T04:00:00+0000"}, {"count": 1, "pub_date": "2014-10-17T00:00:00Z"}, {"count": 1, "pub_date": "2016-11-21T17:58:51Z"}, {"count": 1, "pub_date": "2017-01-25T00:59:17+0000"}, {"count": 2, "pub_date": "2016-08-30T04:00:00+0000"}, {"count": 1, "pub_date": "2015-09-25T00:00:00Z"}, {"count": 1, "pub_date": "2015-05-23T00:00:00Z"}, {"count": 1, "pub_date": "2015-03-31T06:05:27Z"}, {"count": 1, "pub_date": "2016-02-02T05:00:00Z"}, {"count": 1, "pub_date": "2015-12-30T00:00:00Z"}, {"count": 1, "pub_date": "2014-07-10T00:00:00Z"}, {"count": 1, "pub_date": "2016-06-05T00:00:00Z"}, {"count": 1, "pub_date": "2017-01-04T16:42:20+0000"}, {"count": 1, "pub_date": "2015-10-26T00:00:00Z"}, {"count": 1, "pub_date": "2015-06-22T00:00:00Z"}, {"count": 1, "pub_date": "2015-05-08T00:00:00Z"}, {"count": 1, "pub_date": "2015-05-05T17:45:50Z"}, {"count": 1, "pub_date": "2016-09-11T04:00:00+0000"}, {"count": 1, "pub_date": "2014-12-05T12:41:18Z"}, {"count": 2, "pub_date": "2014-10-22T19:08:35Z"}, {"count": 1, "pub_date": "2017-01-07T14:30:03+0000"}, {"count": 1, "pub_date": "2015-01-30T06:17:34Z"}, {"count": 1, "pub_date": "2016-10-03T04:00:00+0000"}, {"count": 1, "pub_date": "2016-02-24T05:45:30Z"}, {"count": 2, "pub_date": "2016-04-23T00:00:00Z"}, {"count": 1, "pub_date": "2016-12-07T15:19:04+0000"}, {"count": 1, "pub_date": "2014-09-15T07:00:29Z"}, {"count": 1, "pub_date": "2016-07-13T00:00:00Z"}, {"count": 1, "pub_date": "2015-09-09T08:54:48Z"}, {"count": 2, "pub_date": "2015-10-01T00:00:00Z"}, {"count": 1, "pub_date": "2016-12-20T00:39:55+0000"}, {"count": 1, "pub_date": "2016-06-03T20:01:09+0000"}, {"count": 1, "pub_date": "2014-07-07T20:04:13Z"}, {"count": 1, "pub_date": "2015-08-19T00:00:00Z"}, {"count": 1, "pub_date": "2015-10-19T00:00:00Z"}, {"count": 1, "pub_date": "2014-09-12T12:12:50Z"}, {"count": 1, "pub_date": "2016-06-15T17:28:42+0000"}, {"count": 1, "pub_date": "2014-09-19T14:05:53Z"}, {"count": 2, "pub_date": "2015-10-08T00:00:00Z"}, {"count": 1, "pub_date": "2014-07-21T00:00:00Z"}, {"count": 2, "pub_date": "2014-06-26T00:00:00Z"}, {"count": 2, "pub_date": "2014-10-28T00:58:25Z"}, {"count": 1, "pub_date": "2016-12-15T04:10:32+0000"}, {"count": 2, "pub_date": "2016-05-05T00:00:00Z"}, {"count": 1, "pub_date": "2016-12-20T13:23:40+0000"}, {"count": 2, "pub_date": "2014-12-15T18:05:29Z"}, {"count": 1, "pub_date": "2015-09-29T09:28:18Z"}, {"count": 1, "pub_date": "2014-10-18T00:00:00Z"}, {"count": 1, "pub_date": "2016-03-08T05:55:30Z"}, {"count": 1, "pub_date": "2015-10-08T23:47:45Z"}, {"count": 1, "pub_date": "2016-10-21T17:38:43+0000"}, {"count": 2, "pub_date": "2015-04-03T00:00:00Z"}, {"count": 1, "pub_date": "2014-09-03T00:00:00Z"}, {"count": 1, "pub_date": "2016-04-16T01:40:23Z"}, {"count": 1, "pub_date": "2017-02-10T20:17:07+0000"}, {"count": 2, "pub_date": "2014-10-31T06:57:33Z"}, {"count": 4, "pub_date": "2015-06-25T00:00:00Z"}, {"count": 4, "pub_date": "2016-02-23T00:00:00Z"}, {"count": 1, "pub_date": "2016-04-24T00:00:00Z"}, {"count": 1, "pub_date": "2016-01-27T09:47:02Z"}, {"count": 1, "pub_date": "2016-07-28T00:00:00Z"}, {"count": 1, "pub_date": "2014-06-16T06:27:29Z"}, {"count": 1, "pub_date": "2015-08-09T00:00:00Z"}, {"count": 1, "pub_date": "2015-12-16T00:00:00Z"}, {"count": 3, "pub_date": "2015-12-10T00:00:00Z"}, {"count": 1, "pub_date": "2015-08-27T00:00:00Z"}, {"count": 1, "pub_date": "2016-10-08T04:00:00+0000"}, {"count": 1, "pub_date": "2016-01-25T09:32:48Z"}, {"count": 1, "pub_date": "2016-02-02T06:04:47Z"}, {"count": 2, "pub_date": "2016-01-28T00:00:00Z"}, {"count": 1, "pub_date": "2015-07-22T09:36:48Z"}, {"count": 1, "pub_date": "2016-05-21T00:00:00Z"}, {"count": 1, "pub_date": "2014-09-10T07:00:39Z"}, {"count": 1, "pub_date": "2015-06-08T15:56:27Z"}, {"count": 1, "pub_date": "2015-07-02T00:00:00Z"}, {"count": 1, "pub_date": "2014-07-16T00:00:00Z"}, {"count": 1, "pub_date": "2015-12-05T00:00:00Z"}, {"count": 1, "pub_date": "2014-12-04T00:00:00Z"}, {"count": 1, "pub_date": "2016-10-07T04:00:00+0000"}, {"count": 1, "pub_date": "2016-08-24T04:00:00+0000"}, {"count": 1, "pub_date": "2016-12-29T08:02:06+0000"}, {"count": 1, "pub_date": "2016-10-18T13:00:17+0000"}, {"count": 1, "pub_date": "2017-01-18T10:00:26+0000"}, {"count": 1, "pub_date": "2015-05-27T15:23:12Z"}, {"count": 1, "pub_date": "2014-06-17T13:00:39Z"}, {"count": 1, "pub_date": "2016-01-30T00:00:00Z"}, {"count": 4, "pub_date": "2016-02-18T00:00:00Z"}, {"count": 3, "pub_date": "2016-03-30T00:00:00Z"}, {"count": 1, "pub_date": "2015-01-30T13:55:02Z"}, {"count": 3, "pub_date": "2015-11-12T00:00:00Z"}, {"count": 1, "pub_date": "2016-03-02T05:00:00Z"}, {"count": 1, "pub_date": "2014-07-31T00:00:00Z"}, {"count": 1, "pub_date": "2014-06-24T00:01:30Z"}, {"count": 1, "pub_date": "2014-10-20T00:00:00Z"}, {"count": 1, "pub_date": "2014-12-05T17:19:53Z"}, {"count": 1, "pub_date": "2015-09-13T00:00:00Z"}, {"count": 4, "pub_date": "2016-09-22T04:00:00+0000"}, {"count": 1, "pub_date": "2015-08-13T00:00:00Z"}, {"count": 1, "pub_date": "2014-10-05T22:29:04Z"}, {"count": 1, "pub_date": "2014-10-07T16:57:17Z"}, {"count": 1, "pub_date": "2014-10-23T06:07:28Z"}, {"count": 1, "pub_date": "2017-01-23T16:12:52+0000"}, {"count": 1, "pub_date": "2017-02-03T19:42:40+0000"}, {"count": 1, "pub_date": "2014-09-11T07:00:30Z"}, {"count": 1, "pub_date": "2015-09-28T10:23:29Z"}, {"count": 1, "pub_date": "2014-11-03T04:31:42Z"}, {"count": 1, "pub_date": "2016-10-04T04:00:00+0000"}, {"count": 1, "pub_date": "2015-07-22T00:00:00Z"}, {"count": 1, "pub_date": "2016-11-03T16:22:57Z"}, {"count": 1, "pub_date": "2014-09-09T16:04:18Z"}, {"count": 1, "pub_date": "2015-12-02T00:00:00Z"}, {"count": 1, "pub_date": "2014-09-12T16:13:23Z"}, {"count": 2, "pub_date": "2015-09-21T00:00:00Z"}, {"count": 2, "pub_date": "2016-04-28T00:00:00Z"}, {"count": 1, "pub_date": "2017-02-01T01:38:43+0000"}, {"count": 1, "pub_date": "2016-02-19T15:20:23Z"}, {"count": 1, "pub_date": "2014-09-05T06:32:18Z"}, {"count": 1, "pub_date": "2014-07-16T09:00:01Z"}, {"count": 2, "pub_date": "2015-02-12T00:00:00Z"}, {"count": 1, "pub_date": "2015-09-04T00:00:00Z"}, {"count": 1, "pub_date": "2016-04-07T04:00:00Z"}, {"count": 1, "pub_date": "2016-03-16T06:16:47Z"}, {"count": 1, "pub_date": "2015-03-17T00:00:00Z"}, {"count": 1, "pub_date": "2015-12-09T16:51:29Z"}, {"count": 1, "pub_date": "2016-07-20T00:00:00Z"}, {"count": 1, "pub_date": "2016-11-17T17:26:23Z"}, {"count": 1, "pub_date": "2014-09-23T00:00:00Z"}, {"count": 2, "pub_date": "2016-09-09T04:00:00+0000"}, {"count": 2, "pub_date": "2014-06-25T08:23:45Z"}, {"count": 1, "pub_date": "2014-06-19T11:52:23Z"}, {"count": 3, "pub_date": "2014-10-27T00:00:00Z"}, {"count": 2, "pub_date": "2014-05-30T00:00:00Z"}, {"count": 1, "pub_date": "2014-09-30T02:56:59Z"}, {"count": 1, "pub_date": "2015-10-19T09:35:02Z"}, {"count": 1, "pub_date": "2017-01-04T10:00:32+0000"}, {"count": 2, "pub_date": "2016-08-25T04:00:00+0000"}, {"count": 1, "pub_date": "2014-10-24T00:00:00Z"}, {"count": 1, "pub_date": "2016-07-03T00:00:00Z"}, {"count": 1, "pub_date": "2014-09-19T10:13:23Z"}, {"count": 1, "pub_date": "2015-03-27T14:19:20Z"}, {"count": 1, "pub_date": "2015-02-09T00:00:00Z"}, {"count": 1, "pub_date": "2015-02-19T00:00:00Z"}, {"count": 1, "pub_date": "2014-09-09T12:30:00Z"}, {"count": 1, "pub_date": "2017-01-25T16:49:38+0000"}, {"count": 1, "pub_date": "2015-05-26T10:53:10Z"}, {"count": 2, "pub_date": "2014-07-23T00:00:00Z"}, {"count": 1, "pub_date": "2015-03-10T06:32:25Z"}, {"count": 2, "pub_date": "2016-09-14T04:00:00+0000"}, {"count": 1, "pub_date": "2017-01-05T21:29:04+0000"}, {"count": 1, "pub_date": "2016-12-02T17:42:31+0000"}, {"count": 1, "pub_date": "2017-01-29T19:27:24+0000"}, {"count": 2, "pub_date": "2016-09-01T04:00:00+0000"}, {"count": 1, "pub_date": "2015-05-21T00:00:00Z"}, {"count": 1, "pub_date": "2015-03-10T15:00:59Z"}, {"count": 1, "pub_date": "2016-11-23T17:40:22+0000"}, {"count": 2, "pub_date": "2016-06-10T00:00:00Z"}, {"count": 1, "pub_date": "2014-06-11T13:09:56Z"}, {"count": 1, "pub_date": "2015-08-11T00:00:00Z"}, {"count": 2, "pub_date": "2014-11-13T00:00:00Z"}, {"count": 1, "pub_date": "2016-04-23T04:00:00Z"}, {"count": 1, "pub_date": "2015-02-23T06:22:39Z"}, {"count": 1, "pub_date": "2014-10-28T14:56:35Z"}, {"count": 1, "pub_date": "2014-12-08T14:15:40Z"}, {"count": 1, "pub_date": "2014-12-03T00:00:00Z"}, {"count": 1, "pub_date": "2016-12-03T14:30:04+0000"}, {"count": 1, "pub_date": "2016-12-07T18:11:43+0000"}, {"count": 1, "pub_date": "2016-04-02T00:00:00Z"}, {"count": 1, "pub_date": "2014-12-08T12:47:07Z"}, {"count": 4, "pub_date": "2016-04-29T00:00:00Z"}, {"count": 1, "pub_date": "2014-09-26T16:05:15Z"}, {"count": 2, "pub_date": "2016-08-30T09:50:28+0000"}, {"count": 1, "pub_date": "2015-12-12T00:00:00Z"}, {"count": 1, "pub_date": "2015-10-22T00:00:00Z"}, {"count": 1, "pub_date": "2016-01-26T06:09:59Z"}, {"count": 1, "pub_date": "2017-02-01T23:30:24+0000"}, {"count": 1, "pub_date": "2015-03-12T05:30:12Z"}, {"count": 1, "pub_date": "2016-08-19T19:54:43+0000"}, {"count": 1, "pub_date": "2016-10-25T10:09:06+0000"}, {"count": 2, "pub_date": "2016-05-03T00:00:00Z"}, {"count": 1, "pub_date": "2016-01-09T00:00:00Z"}, {"count": 1, "pub_date": "2016-04-13T15:44:59+0000"}, {"count": 1, "pub_date": "2016-09-18T04:00:00+0000"}, {"count": 4, "pub_date": "2015-04-09T00:00:00Z"}, {"count": 1, "pub_date": "2014-08-19T00:00:00Z"}, {"count": 1, "pub_date": "2016-03-20T00:00:00Z"}, {"count": 1, "pub_date": "2015-12-11T05:57:41Z"}, {"count": 1, "pub_date": "2016-11-09T21:55:56Z"}, {"count": 2, "pub_date": "2016-02-13T00:00:00Z"}, {"count": 1, "pub_date": "2014-08-28T00:00:00Z"}, {"count": 1, "pub_date": "2016-10-12T04:00:00+0000"}, {"count": 1, "pub_date": "2016-05-02T00:00:00Z"}, {"count": 1, "pub_date": "2016-02-02T09:21:55Z"}, {"count": 1, "pub_date": "2016-12-14T18:18:06+0000"}, {"count": 1, "pub_date": "2014-09-17T06:33:28Z"}, {"count": 1, "pub_date": "2016-04-17T00:00:00Z"}, {"count": 1, "pub_date": "2014-08-15T16:16:40Z"}, {"count": 1, "pub_date": "2015-06-23T09:24:39Z"}, {"count": 1, "pub_date": "2014-11-17T03:34:37Z"}, {"count": 2, "pub_date": "2015-02-27T00:00:00Z"}, {"count": 1, "pub_date": "2014-08-18T07:00:01Z"}, {"count": 2, "pub_date": "2015-10-29T00:00:00Z"}, {"count": 1, "pub_date": "2014-10-03T00:00:00Z"}, {"count": 2, "pub_date": "2016-06-24T00:00:00Z"}, {"count": 1, "pub_date": "2017-01-09T00:49:03+0000"}, {"count": 1, "pub_date": "2015-02-08T05:30:52Z"}, {"count": 1, "pub_date": "2014-09-25T00:00:00Z"}, {"count": 1, "pub_date": "2014-09-24T07:00:09Z"}, {"count": 1, "pub_date": "2017-01-24T01:18:14+0000"}, {"count": 1, "pub_date": "2014-06-26T04:48:06Z"}, {"count": 1, "pub_date": "2015-03-19T00:00:00Z"}, {"count": 1, "pub_date": "2016-06-13T00:00:00Z"}, {"count": 1, "pub_date": "2015-05-19T09:00:38Z"}, {"count": 2, "pub_date": "2015-12-15T00:00:00Z"}, {"count": 1, "pub_date": "2015-02-10T17:29:39Z"}, {"count": 2, "pub_date": "2015-11-09T12:30:51Z"}, {"count": 1, "pub_date": "2015-04-14T16:46:01Z"}, {"count": 1, "pub_date": "2016-09-07T21:37:09+0000"}, {"count": 2, "pub_date": "2015-08-14T00:00:00Z"}, {"count": 1, "pub_date": "2016-06-26T00:00:00Z"}, {"count": 1, "pub_date": "2015-09-29T00:00:00Z"}, {"count": 1, "pub_date": "2014-12-25T00:00:00Z"}, {"count": 1, "pub_date": "2014-11-27T00:00:00Z"}, {"count": 3, "pub_date": "2015-03-12T00:00:00Z"}, {"count": 3, "pub_date": "2014-06-19T00:00:00Z"}, {"count": 2, "pub_date": "2014-10-21T00:00:00Z"}, {"count": 1, "pub_date": "2014-09-12T06:00:03Z"}, {"count": 1, "pub_date": "2017-02-05T20:19:06+0000"}, {"count": 3, "pub_date": "2016-03-31T00:00:00Z"}, {"count": 3, "pub_date": "2014-10-23T00:00:00Z"}, {"count": 2, "pub_date": "2015-03-06T00:00:00Z"}, {"count": 1, "pub_date": "2014-09-03T09:32:46Z"}, {"count": 1, "pub_date": "2015-01-16T22:04:16Z"}, {"count": 1, "pub_date": "2015-01-08T00:00:00Z"}, {"count": 1, "pub_date": "2015-11-11T11:00:15Z"}, {"count": 1, "pub_date": "2016-11-20T21:56:52Z"}, {"count": 1, "pub_date": "2014-06-03T08:44:20Z"}, {"count": 1, "pub_date": "2016-02-17T05:47:31Z"}, {"count": 1, "pub_date": "2015-06-10T00:00:00Z"}, {"count": 1, "pub_date": "2014-08-17T21:22:30Z"}, {"count": 1, "pub_date": "2014-09-28T09:00:32Z"}, {"count": 1, "pub_date": "2015-11-30T06:09:34Z"}, {"count": 1, "pub_date": "2016-12-29T03:50:09+0000"}, {"count": 1, "pub_date": "2016-07-16T00:00:00Z"}, {"count": 2, "pub_date": "2015-05-16T00:00:00Z"}, {"count": 1, "pub_date": "2015-01-16T00:00:00Z"}, {"count": 1, "pub_date": "2015-09-14T19:30:49Z"}, {"count": 2, "pub_date": "2015-04-20T00:00:00Z"}, {"count": 1, "pub_date": "2015-05-17T14:21:47Z"}, {"count": 1, "pub_date": "2014-11-04T11:45:51Z"}, {"count": 1, "pub_date": "2014-08-13T11:53:04Z"}, {"count": 1, "pub_date": "2016-09-13T10:00:14+0000"}, {"count": 3, "pub_date": "2015-08-29T00:00:00Z"}, {"count": 2, "pub_date": "2016-05-26T00:00:00Z"}, {"count": 1, "pub_date": "2016-01-25T00:00:00Z"}, {"count": 1, "pub_date": "2014-10-28T00:00:00Z"}, {"count": 1, "pub_date": "2016-03-22T11:15:19Z"}, {"count": 1, "pub_date": "2014-09-23T19:31:22Z"}, {"count": 1, "pub_date": "2017-01-05T16:24:11+0000"}, {"count": 2, "pub_date": "2016-03-23T00:00:00Z"}, {"count": 1, "pub_date": "2016-05-08T00:00:00Z"}, {"count": 2, "pub_date": "2014-05-29T00:00:00Z"}, {"count": 1, "pub_date": "2015-10-28T06:07:37Z"}, {"count": 1, "pub_date": "2015-06-26T17:36:34Z"}, {"count": 5, "pub_date": "2016-03-05T00:00:00Z"}, {"count": 2, "pub_date": "2014-09-11T13:35:48Z"}, {"count": 1, "pub_date": "2015-01-28T00:00:00Z"}, {"count": 2, "pub_date": "2016-04-26T00:00:00Z"}, {"count": 1, "pub_date": "2016-07-09T00:00:00Z"}, {"count": 1, "pub_date": "2016-01-21T00:00:00Z"}, {"count": 1, "pub_date": "2014-07-23T06:59:16Z"}, {"count": 1, "pub_date": "2015-11-14T00:00:00Z"}, {"count": 1, "pub_date": "2014-09-08T19:43:45Z"}, {"count": 1, "pub_date": "2015-04-16T00:00:00Z"}, {"count": 1, "pub_date": "2016-11-06T20:46:13+0000"}, {"count": 1, "pub_date": "2016-04-14T00:49:26Z"}, {"count": 2, "pub_date": "2016-12-06T17:41:09+0000"}, {"count": 1, "pub_date": "2016-07-14T00:00:00Z"}, {"count": 1, "pub_date": "2015-09-05T00:00:00Z"}, {"count": 1, "pub_date": "2015-01-05T09:03:03Z"}, {"count": 1, "pub_date": "2014-06-19T00:01:26Z"}, {"count": 2, "pub_date": "2016-07-05T00:00:00Z"}, {"count": 3, "pub_date": "2014-10-31T00:00:00Z"}, {"count": 1, "pub_date": "2015-07-31T00:00:00Z"}, {"count": 2, "pub_date": "2015-05-25T20:34:07Z"}, {"count": 2, "pub_date": "2016-03-18T00:00:00Z"}, {"count": 1, "pub_date": "2016-09-30T04:00:00+0000"}, {"count": 1, "pub_date": "2016-04-20T00:00:00Z"}, {"count": 1, "pub_date": "2015-11-09T05:30:28Z"}, {"count": 3, "pub_date": "2016-02-17T00:00:00Z"}, {"count": 1, "pub_date": "2016-10-29T13:30:25+0000"}, {"count": 1, "pub_date": "2016-05-09T00:00:00Z"}, {"count": 1, "pub_date": "2014-12-10T12:36:46Z"}, {"count": 4, "pub_date": "2015-01-30T00:00:00Z"}, {"count": 1, "pub_date": "2015-02-02T20:56:34Z"}, {"count": 1, "pub_date": "2015-08-26T16:32:14Z"}, {"count": 1, "pub_date": "2016-12-05T13:01:22+0000"}, {"count": 1, "pub_date": "2014-09-09T08:00:12Z"}, {"count": 1, "pub_date": "2014-10-23T13:00:45Z"}, {"count": 1, "pub_date": "2016-10-31T16:31:10+0000"}, {"count": 1, "pub_date": "2014-06-30T17:13:05Z"}, {"count": 2, "pub_date": "2015-07-18T00:00:00Z"}, {"count": 1, "pub_date": "2015-02-05T00:00:00Z"}, {"count": 1, "pub_date": "2015-09-09T06:15:00Z"}, {"count": 1, "pub_date": "2016-11-30T11:00:13+0000"}, {"count": 1, "pub_date": "2016-09-02T09:49:48+0000"}, {"count": 1, "pub_date": "2015-03-16T00:00:00Z"}, {"count": 1, "pub_date": "2014-12-11T00:00:00Z"}, {"count": 1, "pub_date": "2015-11-12T06:10:19Z"}, {"count": 1, "pub_date": "2014-09-09T17:22:20Z"}, {"count": 1, "pub_date": "2016-10-26T20:17:06+0000"}, {"count": 1, "pub_date": "2016-12-16T15:18:36+0000"}, {"count": 1, "pub_date": "2016-05-16T21:42:33Z"}, {"count": 2, "pub_date": "2014-09-10T20:01:18Z"}, {"count": 1, "pub_date": "2014-09-04T00:00:00Z"}, {"count": 2, "pub_date": "2015-09-19T00:00:00Z"}, {"count": 2, "pub_date": "2015-10-05T00:00:00Z"}, {"count": 1, "pub_date": "2016-01-19T00:00:00Z"}, {"count": 1, "pub_date": "2015-10-19T13:04:46Z"}, {"count": 1, "pub_date": "2014-10-08T21:43:25Z"}, {"count": 1, "pub_date": "2016-12-29T08:00:44+0000"}, {"count": 2, "pub_date": "2016-04-30T00:00:00Z"}, {"count": 1, "pub_date": "2015-05-27T09:17:51Z"}, {"count": 2, "pub_date": "2015-02-13T00:00:00Z"}, {"count": 3, "pub_date": "2016-01-07T00:00:00Z"}, {"count": 1, "pub_date": "2014-09-19T07:00:53Z"}, {"count": 1, "pub_date": "2016-04-19T04:00:00Z"}, {"count": 3, "pub_date": "2014-09-05T00:00:00Z"}, {"count": 1, "pub_date": "2014-09-24T16:12:48Z"}, {"count": 1, "pub_date": "2016-05-10T00:00:00Z"}, {"count": 1, "pub_date": "2016-06-30T00:00:00Z"}, {"count": 1, "pub_date": "2015-05-06T00:00:00Z"}, {"count": 1, "pub_date": "2016-03-09T00:00:00Z"}, {"count": 1, "pub_date": "2016-08-18T04:00:00+0000"}, {"count": 1, "pub_date": "2014-07-09T17:56:55Z"}, {"count": 2, "pub_date": "2016-07-27T00:00:00Z"}, {"count": 1, "pub_date": "2015-01-27T00:00:00Z"}, {"count": 1, "pub_date": "2014-12-28T00:00:00Z"}, {"count": 1, "pub_date": "2014-09-11T21:11:55Z"}, {"count": 1, "pub_date": "2017-01-27T01:06:24+0000"}, {"count": 1, "pub_date": "2015-04-13T18:00:31Z"}, {"count": 1, "pub_date": "2015-04-01T06:21:53Z"}, {"count": 1, "pub_date": "2016-03-13T00:00:00Z"}, {"count": 4, "pub_date": "2016-02-20T00:00:00Z"}, {"count": 1, "pub_date": "2015-12-30T09:49:04Z"}, {"count": 1, "pub_date": "2014-10-16T09:19:55Z"}, {"count": 1, "pub_date": "2014-12-04T17:21:26Z"}, {"count": 1, "pub_date": "2016-06-21T00:00:00Z"}, {"count": 1, "pub_date": "2014-09-05T23:58:50Z"}, {"count": 2, "pub_date": "2015-11-13T00:00:00Z"}, {"count": 1, "pub_date": "2016-09-28T04:00:00+0000"}, {"count": 1, "pub_date": "2014-07-13T07:00:04Z"}, {"count": 2, "pub_date": "2014-08-07T00:00:00Z"}, {"count": 6, "pub_date": "2015-09-10T00:00:00Z"}, {"count": 1, "pub_date": "2014-10-31T20:08:13Z"}, {"count": 1, "pub_date": "2016-01-07T05:59:36Z"}, {"count": 1, "pub_date": "2014-09-17T21:00:17Z"}, {"count": 1, "pub_date": "2016-08-20T04:00:00+0000"}, {"count": 1, "pub_date": "2017-02-22T16:10:37+0000"}, {"count": 1, "pub_date": "2016-11-07T16:16:45Z"}, {"count": 2, "pub_date": "2015-04-23T00:00:00Z"}, {"count": 1, "pub_date": "2014-09-06T00:00:00Z"}, {"count": 1, "pub_date": "2014-11-06T14:55:54Z"}, {"count": 1, "pub_date": "2017-01-21T00:25:18+0000"}, {"count": 1, "pub_date": "2016-11-25T21:33:35+0000"}, {"count": 1, "pub_date": "2016-07-29T00:00:00Z"}, {"count": 1, "pub_date": "2017-01-01T17:39:17+0000"}, {"count": 1, "pub_date": "2014-06-19T07:43:20Z"}, {"count": 1, "pub_date": "2015-12-07T00:00:00Z"}, {"count": 1, "pub_date": "2014-11-20T00:00:00Z"}, {"count": 2, "pub_date": "2015-10-21T00:00:00Z"}, {"count": 1, "pub_date": "2015-11-20T16:18:11Z"}, {"count": 1, "pub_date": "2015-09-22T08:49:18Z"}, {"count": 2, "pub_date": "2015-03-02T06:26:18Z"}, {"count": 1, "pub_date": "2014-11-24T08:22:26Z"}, {"count": 1, "pub_date": "2016-07-26T00:00:00Z"}, {"count": 1, "pub_date": "2016-02-23T06:31:50Z"}, {"count": 2, "pub_date": "2016-05-20T00:00:00Z"}, {"count": 1, "pub_date": "2014-10-16T08:22:15Z"}, {"count": 2, "pub_date": "2015-01-15T00:00:00Z"}, {"count": 3, "pub_date": "2016-01-23T00:00:00Z"}, {"count": 1, "pub_date": "2015-07-24T00:00:00Z"}, {"count": 1, "pub_date": "2014-12-30T11:30:00Z"}, {"count": 1, "pub_date": "2016-02-26T05:55:24Z"}, {"count": 1, "pub_date": "2014-09-23T06:26:42Z"}, {"count": 2, "pub_date": "2014-06-12T00:00:00Z"}, {"count": 1, "pub_date": "2016-07-30T00:00:00Z"}, {"count": 1, "pub_date": "2016-07-31T00:00:00Z"}, {"count": 1, "pub_date": "2016-05-27T00:00:00Z"}, {"count": 1, "pub_date": "2017-01-04T20:21:33+0000"}, {"count": 1, "pub_date": "2014-10-31T07:00:56Z"}, {"count": 1, "pub_date": "2014-09-03T14:19:02Z"}, {"count": 2, "pub_date": "2015-07-17T00:00:00Z"}, {"count": 1, "pub_date": "2015-09-01T00:00:00Z"}, {"count": 1, "pub_date": "2016-09-23T18:38:27+0000"}, {"count": 1, "pub_date": "2015-01-29T00:00:00Z"}, {"count": 1, "pub_date": "2015-09-17T09:00:03Z"}, {"count": 1, "pub_date": "2014-09-18T00:00:00Z"}, {"count": 2, "pub_date": "2014-07-25T00:00:00Z"}, {"count": 1, "pub_date": "2015-12-28T09:44:41Z"}, {"count": 1, "pub_date": "2015-12-20T00:00:00Z"}, {"count": 1, "pub_date": "2015-05-01T17:09:17Z"}, {"count": 1, "pub_date": "2014-09-21T22:52:34Z"}, {"count": 1, "pub_date": "2017-01-06T01:57:52+0000"}, {"count": 1, "pub_date": "2014-12-03T15:42:30Z"}, {"count": 4, "pub_date": "2014-10-30T00:00:00Z"}, {"count": 1, "pub_date": "2015-07-25T09:15:49Z"}, {"count": 1, "pub_date": "2016-01-29T00:00:00Z"}, {"count": 1, "pub_date": "2016-03-28T00:00:00Z"}, {"count": 1, "pub_date": "2015-11-21T00:00:00Z"}, {"count": 1, "pub_date": "2014-09-08T07:11:43Z"}, {"count": 1, "pub_date": "2014-06-16T16:05:37Z"}, {"count": 1, "pub_date": "2016-02-19T05:43:27Z"}, {"count": 1, "pub_date": "2015-06-13T00:00:00Z"}, {"count": 1, "pub_date": "2014-10-10T00:00:00Z"}, {"count": 1, "pub_date": "2015-03-01T21:00:18Z"}, {"count": 1, "pub_date": "2016-01-27T10:00:07+0000"}, {"count": 2, "pub_date": "2014-10-20T18:45:37Z"}, {"count": 1, "pub_date": "2014-05-29T08:08:26Z"}, {"count": 1, "pub_date": "2016-05-06T00:00:00Z"}, {"count": 2, "pub_date": "2016-05-18T00:00:00Z"}, {"count": 1, "pub_date": "2014-08-25T00:00:00Z"}, {"count": 2, "pub_date": "2016-09-23T04:00:00+0000"}, {"count": 1, "pub_date": "2014-06-19T08:08:26Z"}, {"count": 1, "pub_date": "2015-06-12T00:00:00Z"}, {"count": 2, "pub_date": "2015-06-29T00:00:00Z"}, {"count": 2, "pub_date": "2014-10-09T00:00:00Z"}, {"count": 1, "pub_date": "2016-08-04T04:00:00+0000"}, {"count": 2, "pub_date": "2016-03-01T00:00:00Z"}, {"count": 1, "pub_date": "2015-04-24T17:04:40Z"}, {"count": 1, "pub_date": "2015-09-29T14:23:51Z"}, {"count": 1, "pub_date": "2014-07-07T05:55:17Z"}, {"count": 2, "pub_date": "2016-09-13T04:00:00+0000"}, {"count": 1, "pub_date": "2016-04-18T00:00:00Z"}, {"count": 1, "pub_date": "2014-11-07T00:00:00Z"}, {"count": 2, "pub_date": "2014-09-08T00:00:00Z"}, {"count": 1, "pub_date": "2016-02-15T15:02:12Z"}, {"count": 1, "pub_date": "2015-09-06T00:00:00Z"}, {"count": 3, "pub_date": "2015-03-07T00:00:00Z"}, {"count": 1, "pub_date": "2015-10-02T00:00:00Z"}, {"count": 1, "pub_date": "2015-10-29T19:14:35Z"}, {"count": 1, "pub_date": "2014-08-11T00:00:00Z"}, {"count": 2, "pub_date": "2015-05-30T00:00:00Z"}, {"count": 1, "pub_date": "2016-01-27T05:54:56Z"}, {"count": 1, "pub_date": "2014-10-15T00:00:00Z"}, {"count": 1, "pub_date": "2017-02-01T17:24:07+0000"}, {"count": 1, "pub_date": "2014-10-13T00:00:00Z"}, {"count": 1, "pub_date": "2016-06-04T00:00:00Z"}, {"count": 1, "pub_date": "2015-01-29T11:30:00Z"}, {"count": 1, "pub_date": "2016-03-11T05:47:47Z"}, {"count": 1, "pub_date": "2014-10-31T15:11:52Z"}, {"count": 1, "pub_date": "2015-09-28T00:00:00Z"}, {"count": 1, "pub_date": "2015-12-02T00:01:18Z"}, {"count": 1, "pub_date": "2015-10-02T09:28:00Z"}, {"count": 1, "pub_date": "2014-09-25T15:58:09Z"}, {"count": 1, "pub_date": "2015-01-14T23:01:15Z"}, {"count": 2, "pub_date": "2014-09-10T20:09:19Z"}, {"count": 1, "pub_date": "2017-02-15T10:00:13+0000"}, {"count": 1, "pub_date": "2016-01-17T00:00:00Z"}, {"count": 1, "pub_date": "2014-09-15T15:31:40Z"}, {"count": 1, "pub_date": "2016-04-22T06:10:06Z"}, {"count": 1, "pub_date": "2015-05-28T08:55:55Z"}, {"count": 1, "pub_date": "2016-08-16T11:29:47Z"}, {"count": 1, "pub_date": "2016-08-11T04:00:00+0000"}, {"count": 2, "pub_date": "2016-03-21T00:00:00Z"}, {"count": 1, "pub_date": "2016-06-29T00:00:00Z"}, {"count": 1, "pub_date": "2015-02-18T17:01:05Z"}, {"count": 1, "pub_date": "2014-05-30T13:47:17Z"}, {"count": 1, "pub_date": "2015-01-28T09:00:43Z"}, {"count": 2, "pub_date": "2014-06-02T07:14:45Z"}, {"count": 3, "pub_date": "2015-04-01T00:00:00Z"}, {"count": 2, "pub_date": "2016-08-26T04:00:00+0000"}, {"count": 1, "pub_date": "2014-06-03T00:00:00Z"}, {"count": 1, "pub_date": "2014-10-10T16:52:07Z"}, {"count": 1, "pub_date": "2014-10-29T07:09:46Z"}, {"count": 2, "pub_date": "2014-08-09T00:00:00Z"}, {"count": 5, "pub_date": "2016-02-24T00:00:00Z"}, {"count": 1, "pub_date": "2014-06-27T07:00:29Z"}, {"count": 1, "pub_date": "2014-08-12T00:00:00Z"}, {"count": 3, "pub_date": "2016-03-12T00:00:00Z"}, {"count": 4, "pub_date": "2016-03-02T00:00:00Z"}, {"count": 1, "pub_date": "2015-10-21T12:47:20Z"}, {"count": 1, "pub_date": "2015-09-08T06:27:42Z"}, {"count": 1, "pub_date": "2016-09-05T04:00:00+0000"}, {"count": 1, "pub_date": "2014-09-10T14:35:54Z"}, {"count": 1, "pub_date": "2014-07-11T00:00:00Z"}, {"count": 1, "pub_date": "2016-02-10T00:00:00Z"}, {"count": 4, "pub_date": "2016-06-14T00:00:00Z"}, {"count": 1, "pub_date": "2016-11-25T22:31:39+0000"}, {"count": 1, "pub_date": "2015-09-08T09:22:32Z"}, {"count": 1, "pub_date": "2014-10-10T12:21:43Z"}, {"count": 1, "pub_date": "2017-01-07T00:53:46+0000"}, {"count": 2, "pub_date": "2014-11-03T15:54:06Z"}, {"count": 1, "pub_date": "2014-09-26T00:00:00Z"}, {"count": 1, "pub_date": "2014-12-24T07:00:20Z"}, {"count": 1, "pub_date": "2015-03-04T00:00:00Z"}, {"count": 1, "pub_date": "2015-07-07T00:00:00Z"}, {"count": 1, "pub_date": "2016-01-11T09:41:32Z"}, {"count": 2, "pub_date": "2016-05-13T10:57:43Z"}, {"count": 1, "pub_date": "2016-10-26T10:02:08+0000"}, {"count": 1, "pub_date": "2015-01-02T07:33:57Z"}, {"count": 2, "pub_date": "2015-12-14T00:00:00Z"}, {"count": 1, "pub_date": "2016-03-14T00:00:00Z"}, {"count": 1, "pub_date": "2016-06-15T00:00:00Z"}, {"count": 1, "pub_date": "2015-04-17T00:00:00Z"}, {"count": 1, "pub_date": "2015-11-09T00:00:00Z"}, {"count": 2, "pub_date": "2016-02-21T00:00:00Z"}, {"count": 6, "pub_date": "2016-02-27T00:00:00Z"}, {"count": 4, "pub_date": "2016-05-19T00:00:00Z"}, {"count": 1, "pub_date": "2015-09-09T17:16:21Z"}, {"count": 1, "pub_date": "2015-09-02T00:00:00Z"}, {"count": 1, "pub_date": "2017-01-17T19:30:24+0000"}, {"count": 1, "pub_date": "2014-09-18T15:09:12Z"}, {"count": 1, "pub_date": "2016-10-22T13:30:01+0000"}, {"count": 1, "pub_date": "2015-09-23T00:00:00Z"}, {"count": 1, "pub_date": "2016-05-13T05:52:43Z"}, {"count": 1, "pub_date": "2015-06-17T00:00:00Z"}, {"count": 1, "pub_date": "2015-08-30T00:00:00Z"}, {"count": 1, "pub_date": "2014-08-29T13:36:10Z"}, {"count": 1, "pub_date": "2015-02-06T15:51:42Z"}, {"count": 3, "pub_date": "2016-04-06T00:00:00Z"}, {"count": 1, "pub_date": "2014-06-13T00:00:00Z"}, {"count": 2, "pub_date": "2015-06-18T00:00:00Z"}, {"count": 1, "pub_date": "2014-09-09T16:51:37Z"}, {"count": 1, "pub_date": "2015-09-14T10:31:24Z"}, {"count": 2, "pub_date": "2015-10-10T00:00:00Z"}, {"count": 1, "pub_date": "2014-07-07T00:00:00Z"}, {"count": 1, "pub_date": "2016-12-05T18:08:18+0000"}, {"count": 2, "pub_date": "2014-09-29T00:00:00Z"}, {"count": 1, "pub_date": "2017-01-03T16:39:42+0000"}, {"count": 1, "pub_date": "2016-09-02T04:00:00+0000"}, {"count": 1, "pub_date": "2017-02-14T10:06:43+0000"}, {"count": 1, "pub_date": "2016-07-10T00:00:00Z"}, {"count": 1, "pub_date": "2014-10-03T04:20:13Z"}, {"count": 3, "pub_date": "2015-10-15T00:00:00Z"}, {"count": 2, "pub_date": "2016-03-25T00:00:00Z"}, {"count": 1, "pub_date": "2017-01-02T17:10:45+0000"}, {"count": 1, "pub_date": "2014-09-26T15:35:03Z"}, {"count": 1, "pub_date": "2015-06-05T07:05:44Z"}, {"count": 1, "pub_date": "2016-11-14T17:30:18Z"}, {"count": 1, "pub_date": "2015-12-31T10:12:33Z"}, {"count": 4, "pub_date": "2014-09-11T00:00:00Z"}, {"count": 1, "pub_date": "2014-11-05T17:30:16Z"}, {"count": 2, "pub_date": "2015-02-12T00:05:35Z"}, {"count": 1, "pub_date": "2016-07-15T22:09:53+0000"}, {"count": 1, "pub_date": "2016-03-28T06:03:26Z"}, {"count": 1, "pub_date": "2014-09-10T06:30:26Z"}, {"count": 1, "pub_date": "2015-10-24T00:00:00Z"}, {"count": 1, "pub_date": "2014-10-02T00:00:00Z"}, {"count": 1, "pub_date": "2015-01-14T07:14:14Z"}, {"count": 1, "pub_date": "2014-08-05T23:41:55Z"}, {"count": 2, "pub_date": "2016-03-06T00:00:00Z"}, {"count": 2, "pub_date": "2014-11-10T13:32:14Z"}, {"count": 1, "pub_date": "2015-02-23T19:46:06Z"}, {"count": 1, "pub_date": "2015-12-17T22:03:31Z"}, {"count": 2, "pub_date": "2015-01-09T00:00:00Z"}, {"count": 1, "pub_date": "2015-10-06T06:04:49Z"}, {"count": 1, "pub_date": "2015-05-20T00:00:00Z"}, {"count": 1, "pub_date": "2014-10-02T06:28:01Z"}, {"count": 1, "pub_date": "2016-01-31T00:00:00Z"}, {"count": 1, "pub_date": "2017-01-10T18:30:02+0000"}, {"count": 1, "pub_date": "2015-09-17T00:00:00Z"}, {"count": 2, "pub_date": "2014-07-04T00:00:00Z"}, {"count": 1, "pub_date": "2016-03-24T06:08:15Z"}, {"count": 1, "pub_date": "2015-05-05T00:00:00Z"}, {"count": 1, "pub_date": "2015-12-03T00:00:00Z"}, {"count": 3, "pub_date": "2016-02-03T00:00:00Z"}, {"count": 1, "pub_date": "2016-09-13T14:24:51+0000"}, {"count": 1, "pub_date": "2016-02-19T19:42:42Z"}, {"count": 2, "pub_date": "2014-09-09T00:00:00Z"}, {"count": 1, "pub_date": "2014-12-16T00:05:20Z"}, {"count": 1, "pub_date": "2015-05-08T16:58:24Z"}, {"count": 1, "pub_date": "2015-07-10T09:27:15Z"}, {"count": 1, "pub_date": "2015-07-16T00:00:00Z"}, {"count": 1, "pub_date": "2015-03-19T20:40:00Z"}, {"count": 1, "pub_date": "2014-09-17T00:00:00Z"}, {"count": 1, "pub_date": "2015-09-09T00:00:00Z"}, {"count": 1, "pub_date": "2016-11-30T16:48:21+0000"}, {"count": 1, "pub_date": "2014-08-12T16:35:30Z"}, {"count": 1, "pub_date": "2016-08-02T00:00:00Z"}, {"count": 1, "pub_date": "2014-12-19T21:22:22Z"}, {"count": 4, "pub_date": "2016-08-31T04:00:00+0000"}, {"count": 1, "pub_date": "2015-02-28T14:04:39Z"}, {"count": 1, "pub_date": "2014-11-04T19:39:52Z"}, {"count": 1, "pub_date": "2015-06-30T00:00:00Z"}, {"count": 1, "pub_date": "2015-09-18T00:00:00Z"}, {"count": 4, "pub_date": "2015-03-10T00:00:00Z"}, {"count": 1, "pub_date": "2016-09-03T04:00:00+0000"}, {"count": 1, "pub_date": "2014-05-29T15:54:45Z"}, {"count": 1, "pub_date": "2015-05-25T00:00:00Z"}, {"count": 3, "pub_date": "2016-04-27T00:00:00Z"}, {"count": 1, "pub_date": "2014-10-23T15:22:40Z"}, {"count": 1, "pub_date": "2014-08-08T20:07:52Z"}, {"count": 1, "pub_date": "2017-02-16T16:42:09+0000"}, {"count": 1, "pub_date": "2014-06-23T00:00:00Z"}, {"count": 2, "pub_date": "2014-11-15T00:00:00Z"}, {"count": 1, "pub_date": "2015-04-03T06:24:06Z"}, {"count": 1, "pub_date": "2015-04-09T14:54:26Z"}, {"count": 3, "pub_date": "2016-03-10T00:00:00Z"}, {"count": 6, "pub_date": "2016-09-08T04:00:00+0000"}, {"count": 1, "pub_date": "2015-02-02T17:08:21Z"}, {"count": 7, "pub_date": "2016-02-19T00:00:00Z"}, {"count": 1, "pub_date": "2015-07-23T00:00:00Z"}, {"count": 1, "pub_date": "2017-02-14T15:12:18+0000"}, {"count": 1, "pub_date": "2016-06-18T00:00:00Z"}, {"count": 1, "pub_date": "2015-08-14T09:19:07Z"}, {"count": 1, "pub_date": "2015-06-29T09:46:36Z"}, {"count": 1, "pub_date": "2015-02-09T15:44:34Z"}, {"count": 2, "pub_date": "2014-10-16T00:00:00Z"}, {"count": 1, "pub_date": "2015-07-23T09:30:08Z"}, {"count": 1, "pub_date": "2015-01-28T10:23:57Z"}, {"count": 1, "pub_date": "2016-04-08T15:59:10Z"}, {"count": 1, "pub_date": "2015-03-24T05:30:28Z"}, {"count": 1, "pub_date": "2015-05-12T15:44:08Z"}, {"count": 1, "pub_date": "2015-08-20T00:00:00Z"}, {"count": 1, "pub_date": "2015-01-01T00:00:00Z"}, {"count": 1, "pub_date": "2016-05-25T00:00:00Z"}, {"count": 2, "pub_date": "2015-03-23T00:00:00Z"}, {"count": 1, "pub_date": "2015-10-28T00:00:00Z"}, {"count": 1, "pub_date": "2016-09-21T04:00:00+0000"}, {"count": 1, "pub_date": "2015-08-25T09:15:05Z"}, {"count": 4, "pub_date": "2014-07-24T00:00:00Z"}, {"count": 1, "pub_date": "2015-08-31T17:01:28Z"}, {"count": 1, "pub_date": "2016-04-27T06:47:49Z"}, {"count": 1, "pub_date": "2016-04-12T04:00:00Z"}, {"count": 1, "pub_date": "2016-06-23T00:00:00Z"}, {"count": 4, "pub_date": "2016-02-25T00:00:00Z"}, {"count": 1, "pub_date": "2015-08-07T00:00:00Z"}, {"count": 6, "pub_date": "2015-03-05T00:00:00Z"}, {"count": 1, "pub_date": "2015-09-11T10:24:25Z"}, {"count": 1, "pub_date": "2015-11-17T06:10:55Z"}, {"count": 1, "pub_date": "2015-03-26T05:30:42Z"}, {"count": 4, "pub_date": "2014-09-10T00:00:00Z"}, {"count": 1, "pub_date": "2016-11-17T01:00:17Z"}, {"count": 2, "pub_date": "2016-07-19T04:00:00Z"}, {"count": 2, "pub_date": "2015-09-11T00:00:00Z"}, {"count": 2, "pub_date": "2014-11-07T20:00:44Z"}, {"count": 1, "pub_date": "2014-10-29T00:00:00Z"}, {"count": 2, "pub_date": "2015-08-28T00:00:00Z"}, {"count": 1, "pub_date": "2014-09-09T15:56:08Z"}, {"count": 1, "pub_date": "2014-11-10T00:00:00Z"}, {"count": 1, "pub_date": "2017-01-18T16:39:35+0000"}, {"count": 1, "pub_date": "2017-02-02T17:15:45+0000"}, {"count": 1, "pub_date": "2015-01-02T00:00:00Z"}, {"count": 3, "pub_date": "2015-08-25T00:00:00Z"}, {"count": 1, "pub_date": "2015-01-26T20:17:52Z"}, {"count": 5, "pub_date": "2016-03-22T00:00:00Z"}, {"count": 1, "pub_date": "2015-06-28T09:00:24Z"}, {"count": 5, "pub_date": "2016-03-24T00:00:00Z"}, {"count": 3, "pub_date": "2016-04-22T00:00:00Z"}, {"count": 2, "pub_date": "2015-09-22T00:00:00Z"}, {"count": 2, "pub_date": "2016-03-19T00:00:00Z"}, {"count": 1, "pub_date": "2015-04-07T17:14:06Z"}, {"count": 1, "pub_date": "2015-08-11T11:46:52Z"}, {"count": 1, "pub_date": "2014-09-04T23:32:28Z"}, {"count": 1, "pub_date": "2015-01-06T00:00:00Z"}, {"count": 2, "pub_date": "2015-01-08T18:49:10Z"}, {"count": 1, "pub_date": "2014-06-11T12:13:16Z"}, {"count": 1, "pub_date": "2017-02-01T17:08:15+0000"}, {"count": 6, "pub_date": "2016-06-02T00:00:00Z"}, {"count": 3, "pub_date": "2015-05-28T00:00:00Z"}, {"count": 1, "pub_date": "2015-09-10T09:26:39Z"}, {"count": 1, "pub_date": "2014-10-02T16:09:57Z"}, {"count": 3, "pub_date": "2015-03-26T00:00:00Z"}, {"count": 1, "pub_date": "2014-11-09T07:00:25Z"}, {"count": 1, "pub_date": "2014-09-29T08:24:55Z"}, {"count": 1, "pub_date": "2016-08-06T04:00:00+0000"}, {"count": 1, "pub_date": "2016-02-22T00:00:00Z"}, {"count": 1, "pub_date": "2017-01-30T17:35:02+0000"}, {"count": 2, "pub_date": "2015-10-12T00:00:00Z"}, {"count": 4, "pub_date": "2015-09-24T00:00:00Z"}, {"count": 1, "pub_date": "2016-07-27T18:01:10+0000"}, {"count": 1, "pub_date": "2017-01-21T14:30:03+0000"}, {"count": 1, "pub_date": "2016-03-28T04:00:00Z"}, {"count": 1, "pub_date": "2015-05-14T17:02:40Z"}, {"count": 2, "pub_date": "2016-09-06T04:00:00+0000"}, {"count": 1, "pub_date": "2015-03-13T00:00:00Z"}, {"count": 1, "pub_date": "2016-09-07T04:00:00+0000"}, {"count": 3, "pub_date": "2014-12-24T00:00:00Z"}, {"count": 1, "pub_date": "2014-11-03T22:01:57Z"}, {"count": 2, "pub_date": "2015-02-26T00:00:00Z"}, {"count": 1, "pub_date": "2014-09-30T21:00:16Z"}, {"count": 1, "pub_date": "2016-06-19T00:00:00Z"}]