[{"count": 1, "pub_date": "2014-10-02T11:08:30Z"}, {"count": 1, "pub_date": "2014-09-01T00:00:00Z"}, {"count": 2, "pub_date": "2014-02-13T00:00:00Z"}, {"count": 1, "pub_date": "2016-12-06T03:04:09+0000"}, {"count": 1, "pub_date": "2016-12-28T16:54:04+0000"}, {"count": 1, "pub_date": "2016-04-07T00:00:00Z"}, {"count": 1, "pub_date": "2014-09-15T16:34:42Z"}, {"count": 1, "pub_date": "2016-03-07T00:00:00Z"}, {"count": 1, "pub_date": "2014-01-30T07:03:51Z"}, {"count": 2, "pub_date": "2014-10-16T11:44:52Z"}, {"count": 1, "pub_date": "2014-02-03T07:25:00Z"}, {"count": 1, "pub_date": "2015-03-06T00:00:00Z"}, {"count": 1, "pub_date": "2014-06-26T12:53:02Z"}, {"count": 1, "pub_date": "2015-05-15T12:43:24Z"}, {"count": 1, "pub_date": "2015-04-21T00:00:00Z"}, {"count": 1, "pub_date": "2015-09-15T00:00:00Z"}, {"count": 2, "pub_date": "2014-03-26T10:26:37Z"}, {"count": 1, "pub_date": "2015-04-26T00:00:00Z"}, {"count": 1, "pub_date": "2015-04-08T12:58:47Z"}, {"count": 1, "pub_date": "2015-11-26T00:00:00Z"}, {"count": 1, "pub_date": "2015-07-07T15:43:15Z"}, {"count": 1, "pub_date": "2016-11-03T15:09:11Z"}, {"count": 1, "pub_date": "2017-01-23T02:00:05+0000"}, {"count": 1, "pub_date": "2015-11-12T11:00:56Z"}, {"count": 1, "pub_date": "2016-08-24T04:00:00+0000"}, {"count": 1, "pub_date": "2016-02-26T00:00:00Z"}, {"count": 1, "pub_date": "2016-08-17T04:00:00+0000"}, {"count": 2, "pub_date": "2015-01-22T00:00:00Z"}, {"count": 1, "pub_date": "2014-08-17T09:00:41Z"}, {"count": 3, "pub_date": "2015-04-27T00:00:00Z"}, {"count": 1, "pub_date": "2015-03-23T19:17:46Z"}, {"count": 1, "pub_date": "2016-09-17T04:00:00+0000"}, {"count": 4, "pub_date": "2014-01-28T00:00:00Z"}, {"count": 1, "pub_date": "2017-01-09T00:49:03+0000"}, {"count": 1, "pub_date": "2016-02-12T00:00:00Z"}, {"count": 1, "pub_date": "2016-12-12T00:57:20+0000"}, {"count": 1, "pub_date": "2016-01-22T00:00:00Z"}, {"count": 1, "pub_date": "2015-10-03T00:00:00Z"}, {"count": 1, "pub_date": "2015-05-28T15:48:24Z"}, {"count": 2, "pub_date": "2015-10-23T00:00:00Z"}, {"count": 1, "pub_date": "2017-02-06T10:46:43+0000"}, {"count": 1, "pub_date": "2014-05-28T18:42:52Z"}, {"count": 1, "pub_date": "2014-02-01T00:00:00Z"}, {"count": 1, "pub_date": "2015-04-24T00:00:00Z"}, {"count": 1, "pub_date": "2014-02-04T09:22:45Z"}, {"count": 1, "pub_date": "2015-09-25T09:17:06Z"}, {"count": 1, "pub_date": "2014-05-21T17:08:16Z"}, {"count": 1, "pub_date": "2015-06-20T00:00:00Z"}, {"count": 1, "pub_date": "2016-04-18T18:33:25Z"}, {"count": 1, "pub_date": "2016-12-14T16:30:01+0000"}, {"count": 1, "pub_date": "2016-03-01T00:00:00Z"}, {"count": 1, "pub_date": "2014-07-05T00:00:00Z"}, {"count": 1, "pub_date": "2016-02-01T09:26:12Z"}, {"count": 2, "pub_date": "2014-08-25T06:37:21Z"}, {"count": 1, "pub_date": "2016-02-01T12:00:24Z"}, {"count": 1, "pub_date": "2014-12-08T17:45:32Z"}, {"count": 1, "pub_date": "2015-12-17T00:00:00Z"}, {"count": 1, "pub_date": "2014-08-05T17:26:19Z"}, {"count": 1, "pub_date": "2017-02-21T17:17:13+0000"}, {"count": 1, "pub_date": "2014-07-10T21:00:59Z"}, {"count": 2, "pub_date": "2015-04-18T00:00:00Z"}, {"count": 1, "pub_date": "2015-04-08T00:00:00Z"}, {"count": 1, "pub_date": "2014-11-03T04:31:42Z"}, {"count": 1, "pub_date": "2014-01-28T05:46:34Z"}, {"count": 1, "pub_date": "2014-05-15T11:57:17Z"}, {"count": 1, "pub_date": "2014-12-03T16:19:06Z"}, {"count": 2, "pub_date": "2015-09-12T00:00:00Z"}, {"count": 1, "pub_date": "2015-07-26T15:00:19Z"}, {"count": 1, "pub_date": "2016-04-14T00:00:00Z"}, {"count": 1, "pub_date": "2015-05-29T00:00:00Z"}, {"count": 1, "pub_date": "2014-04-14T15:52:34Z"}, {"count": 1, "pub_date": "2016-05-24T00:00:00Z"}, {"count": 1, "pub_date": "2014-07-24T06:59:43Z"}, {"count": 1, "pub_date": "2016-08-03T04:00:00+0000"}, {"count": 1, "pub_date": "2016-10-05T04:00:00+0000"}, {"count": 1, "pub_date": "2014-07-08T00:01:09Z"}, {"count": 1, "pub_date": "2016-11-16T11:00:20+0000"}, {"count": 1, "pub_date": "2017-01-20T21:35:24+0000"}, {"count": 1, "pub_date": "2016-12-13T18:06:48+0000"}, {"count": 1, "pub_date": "2015-03-10T18:38:52Z"}, {"count": 1, "pub_date": "2016-12-06T14:00:26+0000"}, {"count": 2, "pub_date": "2015-01-23T10:35:25Z"}, {"count": 2, "pub_date": "2015-04-15T00:00:00Z"}, {"count": 1, "pub_date": "2015-12-18T00:00:00Z"}, {"count": 1, "pub_date": "2015-03-04T07:00:49Z"}, {"count": 1, "pub_date": "2014-01-28T11:17:37Z"}, {"count": 1, "pub_date": "2017-01-31T03:03:02+0000"}, {"count": 1, "pub_date": "2015-06-04T00:00:00Z"}, {"count": 1, "pub_date": "2014-06-17T21:25:51Z"}, {"count": 1, "pub_date": "2014-04-24T14:55:00Z"}, {"count": 2, "pub_date": "2016-08-12T04:00:00+0000"}, {"count": 1, "pub_date": "2017-01-01T23:00:24+0000"}, {"count": 2, "pub_date": "2016-03-16T00:00:00Z"}, {"count": 1, "pub_date": "2016-04-13T00:00:00Z"}, {"count": 1, "pub_date": "2015-06-11T00:00:00Z"}, {"count": 1, "pub_date": "2017-01-12T15:33:00+0000"}, {"count": 1, "pub_date": "2014-10-14T16:38:12Z"}, {"count": 1, "pub_date": "2015-04-07T00:01:37Z"}, {"count": 1, "pub_date": "2016-01-16T00:00:00Z"}, {"count": 1, "pub_date": "2016-06-28T00:00:00Z"}, {"count": 2, "pub_date": "2016-09-19T04:00:00+0000"}, {"count": 1, "pub_date": "2015-07-06T00:00:00Z"}, {"count": 1, "pub_date": "2014-03-25T13:15:06Z"}, {"count": 3, "pub_date": "2014-04-17T07:10:00Z"}, {"count": 1, "pub_date": "2017-01-18T10:30:23+0000"}, {"count": 1, "pub_date": "2015-10-15T07:30:51Z"}, {"count": 1, "pub_date": "2017-01-18T10:00:26+0000"}, {"count": 1, "pub_date": "2015-11-24T19:11:27Z"}, {"count": 1, "pub_date": "2015-06-10T18:31:07Z"}, {"count": 1, "pub_date": "2014-04-11T00:00:00Z"}, {"count": 1, "pub_date": "2016-09-29T04:00:00+0000"}, {"count": 1, "pub_date": "2014-05-30T00:00:00Z"}, {"count": 1, "pub_date": "2016-12-25T23:36:51+0000"}, {"count": 1, "pub_date": "2014-11-12T06:35:25Z"}, {"count": 1, "pub_date": "2014-05-30T06:33:40Z"}, {"count": 1, "pub_date": "2015-09-15T09:10:49Z"}, {"count": 1, "pub_date": "2014-04-02T18:03:50Z"}, {"count": 1, "pub_date": "2014-10-24T19:52:23Z"}, {"count": 1, "pub_date": "2016-02-02T05:00:00Z"}, {"count": 1, "pub_date": "2015-09-03T08:30:51Z"}, {"count": 1, "pub_date": "2015-01-11T07:00:45Z"}, {"count": 1, "pub_date": "2014-10-29T13:15:29Z"}, {"count": 1, "pub_date": "2016-06-20T12:32:15Z"}, {"count": 1, "pub_date": "2015-01-06T09:41:28Z"}, {"count": 1, "pub_date": "2015-07-12T15:00:33Z"}, {"count": 1, "pub_date": "2015-05-05T12:30:42Z"}, {"count": 1, "pub_date": "2015-07-01T21:13:44Z"}, {"count": 1, "pub_date": "2016-09-15T18:49:56Z"}, {"count": 1, "pub_date": "2014-04-26T00:00:00Z"}, {"count": 1, "pub_date": "2016-04-23T00:00:00Z"}, {"count": 1, "pub_date": "2014-01-25T16:58:14Z"}, {"count": 2, "pub_date": "2015-07-30T12:46:39Z"}, {"count": 1, "pub_date": "2014-10-10T00:00:00Z"}, {"count": 1, "pub_date": "2014-09-15T07:00:29Z"}, {"count": 1, "pub_date": "2016-07-13T00:00:00Z"}, {"count": 2, "pub_date": "2016-07-20T00:00:00Z"}, {"count": 1, "pub_date": "2014-09-16T00:00:00Z"}, {"count": 3, "pub_date": "2015-08-19T00:00:00Z"}, {"count": 1, "pub_date": "2015-10-19T00:00:00Z"}, {"count": 1, "pub_date": "2017-01-03T16:06:19+0000"}, {"count": 1, "pub_date": "2014-02-24T11:00:00Z"}, {"count": 1, "pub_date": "2016-04-20T09:21:12Z"}, {"count": 1, "pub_date": "2016-07-29T00:00:00Z"}, {"count": 1, "pub_date": "2015-08-12T00:00:00Z"}, {"count": 1, "pub_date": "2014-05-02T00:00:00Z"}, {"count": 1, "pub_date": "2015-01-21T00:00:00Z"}, {"count": 2, "pub_date": "2014-03-21T00:00:00Z"}, {"count": 1, "pub_date": "2014-10-30T00:00:00Z"}, {"count": 1, "pub_date": "2015-09-29T09:28:18Z"}, {"count": 1, "pub_date": "2014-01-31T15:02:12Z"}, {"count": 1, "pub_date": "2016-11-03T16:45:55Z"}, {"count": 1, "pub_date": "2015-02-25T08:00:22Z"}, {"count": 2, "pub_date": "2015-03-25T00:00:00Z"}, {"count": 3, "pub_date": "2015-04-07T13:31:28Z"}, {"count": 1, "pub_date": "2015-09-28T12:00:35Z"}, {"count": 1, "pub_date": "2015-05-27T09:17:51Z"}, {"count": 1, "pub_date": "2016-12-05T15:39:44+0000"}, {"count": 1, "pub_date": "2016-07-28T00:00:00Z"}, {"count": 1, "pub_date": "2015-02-12T06:21:17Z"}, {"count": 2, "pub_date": "2015-12-16T00:00:00Z"}, {"count": 1, "pub_date": "2014-11-17T00:00:00Z"}, {"count": 1, "pub_date": "2014-09-26T17:50:51Z"}, {"count": 1, "pub_date": "2016-01-28T00:00:00Z"}, {"count": 1, "pub_date": "2014-01-31T00:00:00Z"}, {"count": 1, "pub_date": "2016-05-21T00:00:00Z"}, {"count": 1, "pub_date": "2016-12-17T14:30:02+0000"}, {"count": 1, "pub_date": "2014-10-17T07:39:29Z"}, {"count": 1, "pub_date": "2014-02-07T00:00:00Z"}, {"count": 1, "pub_date": "2014-07-31T13:22:26Z"}, {"count": 1, "pub_date": "2014-10-25T16:07:10Z"}, {"count": 2, "pub_date": "2016-03-30T00:00:00Z"}, {"count": 1, "pub_date": "2014-10-04T00:00:00Z"}, {"count": 2, "pub_date": "2014-06-28T07:00:03Z"}, {"count": 1, "pub_date": "2014-06-24T00:01:30Z"}, {"count": 1, "pub_date": "2016-08-04T04:00:00+0000"}, {"count": 1, "pub_date": "2014-03-07T00:00:00Z"}, {"count": 2, "pub_date": "2016-09-22T04:00:00+0000"}, {"count": 1, "pub_date": "2015-03-25T20:30:41Z"}, {"count": 1, "pub_date": "2014-09-25T06:49:26Z"}, {"count": 3, "pub_date": "2014-09-11T07:00:30Z"}, {"count": 1, "pub_date": "2014-08-14T00:00:00Z"}, {"count": 1, "pub_date": "2016-06-24T00:00:00Z"}, {"count": 2, "pub_date": "2016-01-12T18:00:20Z"}, {"count": 1, "pub_date": "2014-07-09T00:00:00Z"}, {"count": 1, "pub_date": "2014-03-25T00:00:00Z"}, {"count": 2, "pub_date": "2016-01-18T00:00:00Z"}, {"count": 1, "pub_date": "2014-08-07T06:59:26Z"}, {"count": 1, "pub_date": "2016-10-26T02:12:24+0000"}, {"count": 1, "pub_date": "2015-06-11T09:39:24Z"}, {"count": 1, "pub_date": "2015-01-18T13:00:37Z"}, {"count": 1, "pub_date": "2015-05-29T17:56:37Z"}, {"count": 2, "pub_date": "2015-02-12T00:00:00Z"}, {"count": 1, "pub_date": "2017-01-27T16:10:57+0000"}, {"count": 1, "pub_date": "2015-09-04T00:00:00Z"}, {"count": 1, "pub_date": "2016-04-07T04:00:00Z"}, {"count": 1, "pub_date": "2016-12-06T17:01:17+0000"}, {"count": 1, "pub_date": "2014-07-09T11:06:25Z"}, {"count": 1, "pub_date": "2015-04-06T22:30:53Z"}, {"count": 2, "pub_date": "2015-10-19T09:35:02Z"}, {"count": 1, "pub_date": "2015-09-06T00:00:00Z"}, {"count": 1, "pub_date": "2014-12-04T00:00:00Z"}, {"count": 1, "pub_date": "2014-03-14T00:00:00Z"}, {"count": 1, "pub_date": "2014-10-17T00:00:00Z"}, {"count": 1, "pub_date": "2014-11-11T11:45:31Z"}, {"count": 1, "pub_date": "2014-07-16T07:00:38Z"}, {"count": 1, "pub_date": "2016-08-25T04:00:00+0000"}, {"count": 3, "pub_date": "2016-05-09T00:00:00Z"}, {"count": 1, "pub_date": "2015-10-02T00:00:00Z"}, {"count": 1, "pub_date": "2015-02-19T00:00:00Z"}, {"count": 1, "pub_date": "2017-01-25T16:49:38+0000"}, {"count": 2, "pub_date": "2016-09-21T21:28:57Z"}, {"count": 2, "pub_date": "2015-04-24T06:17:46Z"}, {"count": 1, "pub_date": "2016-11-28T16:58:30+0000"}, {"count": 1, "pub_date": "2016-09-14T04:00:00+0000"}, {"count": 1, "pub_date": "2017-01-05T21:29:04+0000"}, {"count": 1, "pub_date": "2014-05-27T00:00:00Z"}, {"count": 1, "pub_date": "2014-05-21T00:00:00Z"}, {"count": 4, "pub_date": "2015-08-11T00:00:00Z"}, {"count": 1, "pub_date": "2015-02-23T06:22:39Z"}, {"count": 1, "pub_date": "2014-07-07T06:16:27Z"}, {"count": 1, "pub_date": "2016-03-17T00:00:00Z"}, {"count": 2, "pub_date": "2015-11-14T00:00:00Z"}, {"count": 1, "pub_date": "2016-04-02T00:00:00Z"}, {"count": 1, "pub_date": "2014-02-15T00:00:00Z"}, {"count": 1, "pub_date": "2014-09-22T00:00:00Z"}, {"count": 1, "pub_date": "2015-01-21T06:22:47Z"}, {"count": 1, "pub_date": "2017-01-26T16:58:04+0000"}, {"count": 1, "pub_date": "2015-12-12T00:00:00Z"}, {"count": 1, "pub_date": "2016-06-07T06:17:57Z"}, {"count": 2, "pub_date": "2015-10-22T00:00:00Z"}, {"count": 1, "pub_date": "2014-08-28T20:34:18Z"}, {"count": 1, "pub_date": "2016-03-09T15:05:30Z"}, {"count": 1, "pub_date": "2016-05-31T00:00:00Z"}, {"count": 1, "pub_date": "2014-12-28T07:00:40Z"}, {"count": 1, "pub_date": "2014-08-19T00:00:00Z"}, {"count": 1, "pub_date": "2015-03-02T13:05:50Z"}, {"count": 2, "pub_date": "2016-02-13T00:00:00Z"}, {"count": 1, "pub_date": "2016-07-08T00:00:00Z"}, {"count": 1, "pub_date": "2016-12-14T18:18:06+0000"}, {"count": 1, "pub_date": "2014-12-24T07:06:18Z"}, {"count": 1, "pub_date": "2014-06-26T06:49:12Z"}, {"count": 1, "pub_date": "2014-07-23T15:04:12Z"}, {"count": 1, "pub_date": "2014-09-15T19:12:26Z"}, {"count": 1, "pub_date": "2015-12-09T00:00:00Z"}, {"count": 1, "pub_date": "2015-10-29T00:00:00Z"}, {"count": 1, "pub_date": "2016-03-29T00:00:00Z"}, {"count": 1, "pub_date": "2014-01-27T21:30:55Z"}, {"count": 1, "pub_date": "2014-06-05T00:00:00Z"}, {"count": 1, "pub_date": "2015-05-01T20:55:09Z"}, {"count": 2, "pub_date": "2014-11-28T00:00:00Z"}, {"count": 1, "pub_date": "2015-01-15T20:20:50Z"}, {"count": 1, "pub_date": "2015-05-20T00:00:00Z"}, {"count": 1, "pub_date": "2015-08-10T21:52:53Z"}, {"count": 1, "pub_date": "2014-05-13T13:53:20Z"}, {"count": 1, "pub_date": "2015-08-14T00:00:00Z"}, {"count": 1, "pub_date": "2016-11-15T01:57:16+0000"}, {"count": 1, "pub_date": "2015-09-29T00:00:00Z"}, {"count": 1, "pub_date": "2014-12-25T00:00:00Z"}, {"count": 2, "pub_date": "2015-03-12T00:00:00Z"}, {"count": 1, "pub_date": "2014-09-12T06:00:03Z"}, {"count": 2, "pub_date": "2017-02-16T21:56:05+0000"}, {"count": 1, "pub_date": "2015-04-28T11:33:43Z"}, {"count": 1, "pub_date": "2014-06-18T12:36:09Z"}, {"count": 1, "pub_date": "2016-08-13T04:00:00+0000"}, {"count": 1, "pub_date": "2014-06-25T17:59:07Z"}, {"count": 1, "pub_date": "2015-01-16T22:04:16Z"}, {"count": 1, "pub_date": "2015-02-09T06:28:58Z"}, {"count": 1, "pub_date": "2014-06-03T08:44:20Z"}, {"count": 1, "pub_date": "2016-11-16T17:46:30Z"}, {"count": 1, "pub_date": "2015-05-16T00:00:00Z"}, {"count": 2, "pub_date": "2015-07-13T19:49:45Z"}, {"count": 1, "pub_date": "2014-04-18T00:00:00Z"}, {"count": 1, "pub_date": "2016-07-22T00:00:00Z"}, {"count": 1, "pub_date": "2015-08-29T00:00:00Z"}, {"count": 2, "pub_date": "2014-11-24T07:00:54Z"}, {"count": 1, "pub_date": "2014-11-26T05:00:40Z"}, {"count": 1, "pub_date": "2014-07-10T06:22:34Z"}, {"count": 1, "pub_date": "2015-05-29T09:05:52Z"}, {"count": 2, "pub_date": "2015-09-30T00:00:00Z"}, {"count": 1, "pub_date": "2016-03-23T00:00:00Z"}, {"count": 3, "pub_date": "2014-11-19T23:27:18Z"}, {"count": 2, "pub_date": "2016-01-21T00:00:00Z"}, {"count": 1, "pub_date": "2015-09-30T18:13:43Z"}, {"count": 1, "pub_date": "2016-06-27T00:27:34+0000"}, {"count": 1, "pub_date": "2014-10-24T15:29:28Z"}, {"count": 3, "pub_date": "2014-06-26T00:00:00Z"}, {"count": 3, "pub_date": "2015-04-16T00:00:00Z"}, {"count": 1, "pub_date": "2014-12-24T10:23:41Z"}, {"count": 2, "pub_date": "2014-06-19T00:01:26Z"}, {"count": 1, "pub_date": "2016-12-12T17:53:29+0000"}, {"count": 1, "pub_date": "2016-07-14T09:37:19+0000"}, {"count": 1, "pub_date": "2015-10-23T09:18:40Z"}, {"count": 1, "pub_date": "2015-10-22T09:27:33Z"}, {"count": 2, "pub_date": "2016-07-01T00:00:00Z"}, {"count": 2, "pub_date": "2016-04-20T00:00:00Z"}, {"count": 1, "pub_date": "2014-06-18T12:42:08Z"}, {"count": 1, "pub_date": "2014-11-04T09:47:56Z"}, {"count": 1, "pub_date": "2015-03-10T14:00:09Z"}, {"count": 1, "pub_date": "2015-01-30T00:00:00Z"}, {"count": 1, "pub_date": "2014-09-05T06:54:03Z"}, {"count": 1, "pub_date": "2015-09-04T11:15:19Z"}, {"count": 1, "pub_date": "2015-01-08T15:56:07Z"}, {"count": 1, "pub_date": "2015-09-02T09:15:24Z"}, {"count": 1, "pub_date": "2016-04-29T13:18:44Z"}, {"count": 1, "pub_date": "2015-04-29T08:07:56Z"}, {"count": 1, "pub_date": "2014-02-19T19:52:52Z"}, {"count": 1, "pub_date": "2016-12-16T15:18:36+0000"}, {"count": 2, "pub_date": "2015-10-01T00:00:00Z"}, {"count": 1, "pub_date": "2015-05-06T13:33:01Z"}, {"count": 1, "pub_date": "2014-03-28T07:00:10Z"}, {"count": 1, "pub_date": "2015-12-04T00:00:00Z"}, {"count": 1, "pub_date": "2015-07-24T14:27:45Z"}, {"count": 1, "pub_date": "2014-12-11T14:25:41Z"}, {"count": 1, "pub_date": "2016-08-09T15:20:52+0000"}, {"count": 1, "pub_date": "2014-02-14T12:36:35Z"}, {"count": 1, "pub_date": "2014-09-11T15:21:33Z"}, {"count": 1, "pub_date": "2014-08-26T16:07:16Z"}, {"count": 1, "pub_date": "2015-02-13T06:24:14Z"}, {"count": 1, "pub_date": "2016-04-19T04:00:00Z"}, {"count": 1, "pub_date": "2014-09-15T12:52:54Z"}, {"count": 1, "pub_date": "2016-11-14T00:48:57Z"}, {"count": 1, "pub_date": "2016-03-09T00:00:00Z"}, {"count": 2, "pub_date": "2016-05-12T00:00:00Z"}, {"count": 1, "pub_date": "2014-02-05T16:26:55Z"}, {"count": 1, "pub_date": "2017-01-27T01:06:24+0000"}, {"count": 1, "pub_date": "2015-01-02T10:00:36Z"}, {"count": 2, "pub_date": "2016-07-25T00:00:00Z"}, {"count": 1, "pub_date": "2017-01-26T17:02:58+0000"}, {"count": 1, "pub_date": "2016-06-21T00:00:00Z"}, {"count": 1, "pub_date": "2015-04-16T06:20:52Z"}, {"count": 1, "pub_date": "2015-06-12T15:40:10Z"}, {"count": 1, "pub_date": "2015-09-10T00:00:00Z"}, {"count": 1, "pub_date": "2014-11-21T12:30:40Z"}, {"count": 1, "pub_date": "2017-01-11T15:22:38+0000"}, {"count": 1, "pub_date": "2016-02-06T20:57:45Z"}, {"count": 2, "pub_date": "2014-04-25T00:00:00Z"}, {"count": 1, "pub_date": "2014-07-10T15:10:42Z"}, {"count": 1, "pub_date": "2015-04-23T00:00:00Z"}, {"count": 1, "pub_date": "2014-09-06T00:00:00Z"}, {"count": 1, "pub_date": "2014-03-01T00:00:00Z"}, {"count": 1, "pub_date": "2016-12-14T18:27:17+0000"}, {"count": 2, "pub_date": "2014-07-17T04:47:48Z"}, {"count": 1, "pub_date": "2014-02-28T00:00:00Z"}, {"count": 2, "pub_date": "2015-10-08T00:00:00Z"}, {"count": 1, "pub_date": "2014-10-01T07:03:03Z"}, {"count": 1, "pub_date": "2014-09-08T16:31:50Z"}, {"count": 1, "pub_date": "2017-01-01T17:39:17+0000"}, {"count": 3, "pub_date": "2015-10-21T00:00:00Z"}, {"count": 1, "pub_date": "2015-04-08T15:43:20Z"}, {"count": 1, "pub_date": "2016-12-06T12:37:29+0000"}, {"count": 1, "pub_date": "2014-03-21T07:00:30Z"}, {"count": 1, "pub_date": "2014-09-05T00:00:00Z"}, {"count": 1, "pub_date": "2016-05-20T00:00:00Z"}, {"count": 1, "pub_date": "2014-05-01T00:00:00Z"}, {"count": 1, "pub_date": "2014-02-27T18:43:04Z"}, {"count": 1, "pub_date": "2015-01-15T00:00:00Z"}, {"count": 3, "pub_date": "2016-01-23T00:00:00Z"}, {"count": 1, "pub_date": "2016-11-01T22:21:04+0000"}, {"count": 1, "pub_date": "2015-07-24T00:00:00Z"}, {"count": 1, "pub_date": "2015-08-02T05:52:32Z"}, {"count": 1, "pub_date": "2015-01-14T11:40:25Z"}, {"count": 1, "pub_date": "2015-02-16T05:30:47Z"}, {"count": 1, "pub_date": "2015-04-15T06:42:34Z"}, {"count": 2, "pub_date": "2015-07-17T00:00:00Z"}, {"count": 1, "pub_date": "2014-09-18T07:42:59Z"}, {"count": 1, "pub_date": "2016-11-03T13:00:16Z"}, {"count": 1, "pub_date": "2014-09-18T00:00:00Z"}, {"count": 1, "pub_date": "2017-01-08T21:30:11+0000"}, {"count": 1, "pub_date": "2015-05-14T00:00:00Z"}, {"count": 2, "pub_date": "2015-09-22T06:00:35Z"}, {"count": 1, "pub_date": "2016-08-05T21:37:05+0000"}, {"count": 1, "pub_date": "2015-11-09T09:00:22Z"}, {"count": 1, "pub_date": "2015-02-05T01:43:15Z"}, {"count": 1, "pub_date": "2014-02-05T08:30:43Z"}, {"count": 2, "pub_date": "2015-10-28T12:11:13Z"}, {"count": 1, "pub_date": "2014-04-15T00:00:00Z"}, {"count": 2, "pub_date": "2014-05-19T00:00:00Z"}, {"count": 2, "pub_date": "2015-06-13T00:00:00Z"}, {"count": 1, "pub_date": "2014-02-19T12:21:11Z"}, {"count": 1, "pub_date": "2015-08-17T11:11:00Z"}, {"count": 1, "pub_date": "2014-05-28T06:59:23Z"}, {"count": 1, "pub_date": "2015-01-16T08:57:14Z"}, {"count": 1, "pub_date": "2015-06-29T00:00:00Z"}, {"count": 1, "pub_date": "2014-10-09T00:00:00Z"}, {"count": 1, "pub_date": "2014-10-20T00:00:00Z"}, {"count": 1, "pub_date": "2017-02-03T19:42:40+0000"}, {"count": 1, "pub_date": "2016-10-04T04:00:00+0000"}, {"count": 1, "pub_date": "2016-12-21T18:24:36+0000"}, {"count": 1, "pub_date": "2016-04-06T17:54:49Z"}, {"count": 1, "pub_date": "2015-03-05T14:32:25Z"}, {"count": 1, "pub_date": "2014-04-08T00:00:00Z"}, {"count": 1, "pub_date": "2015-01-02T00:00:00Z"}, {"count": 1, "pub_date": "2015-11-09T05:30:28Z"}, {"count": 2, "pub_date": "2016-10-30T23:55:43+0000"}, {"count": 1, "pub_date": "2016-01-05T00:00:00Z"}, {"count": 3, "pub_date": "2014-10-15T00:00:00Z"}, {"count": 1, "pub_date": "2014-10-13T00:00:00Z"}, {"count": 1, "pub_date": "2016-02-02T09:21:55Z"}, {"count": 1, "pub_date": "2014-07-18T00:00:00Z"}, {"count": 1, "pub_date": "2015-01-09T11:30:00Z"}, {"count": 1, "pub_date": "2014-02-19T14:02:31Z"}, {"count": 3, "pub_date": "2015-09-28T00:00:00Z"}, {"count": 1, "pub_date": "2015-10-02T09:28:00Z"}, {"count": 1, "pub_date": "2016-04-21T00:00:00Z"}, {"count": 1, "pub_date": "2015-07-02T00:00:00Z"}, {"count": 2, "pub_date": "2015-02-26T00:00:00Z"}, {"count": 1, "pub_date": "2016-11-15T17:15:01Z"}, {"count": 1, "pub_date": "2015-06-25T00:00:00Z"}, {"count": 1, "pub_date": "2014-12-11T11:48:08Z"}, {"count": 1, "pub_date": "2015-07-10T06:00:36Z"}, {"count": 1, "pub_date": "2015-01-28T09:00:43Z"}, {"count": 1, "pub_date": "2014-06-03T00:00:00Z"}, {"count": 1, "pub_date": "2014-12-18T00:00:00Z"}, {"count": 1, "pub_date": "2014-08-09T00:00:00Z"}, {"count": 1, "pub_date": "2014-09-22T06:18:50Z"}, {"count": 2, "pub_date": "2016-02-24T00:00:00Z"}, {"count": 1, "pub_date": "2015-09-14T02:28:05Z"}, {"count": 1, "pub_date": "2014-03-27T16:39:19Z"}, {"count": 2, "pub_date": "2015-04-27T07:26:21Z"}, {"count": 1, "pub_date": "2014-12-20T00:00:00Z"}, {"count": 1, "pub_date": "2017-01-07T00:53:46+0000"}, {"count": 2, "pub_date": "2014-09-26T00:00:00Z"}, {"count": 1, "pub_date": "2014-03-31T00:00:00Z"}, {"count": 1, "pub_date": "2015-03-04T00:00:00Z"}, {"count": 1, "pub_date": "2014-01-24T18:28:12Z"}, {"count": 1, "pub_date": "2014-12-24T07:00:20Z"}, {"count": 2, "pub_date": "2016-05-19T00:00:00Z"}, {"count": 1, "pub_date": "2014-11-04T16:00:51Z"}, {"count": 1, "pub_date": "2014-08-26T11:40:33Z"}, {"count": 3, "pub_date": "2015-03-30T08:45:11Z"}, {"count": 1, "pub_date": "2015-09-02T00:00:00Z"}, {"count": 1, "pub_date": "2014-09-09T00:00:00Z"}, {"count": 1, "pub_date": "2015-08-13T16:21:28Z"}, {"count": 1, "pub_date": "2014-05-13T19:23:12Z"}, {"count": 1, "pub_date": "2014-02-04T21:15:23Z"}, {"count": 1, "pub_date": "2014-04-11T08:41:43Z"}, {"count": 1, "pub_date": "2015-07-15T06:28:23Z"}, {"count": 1, "pub_date": "2016-01-24T00:00:00Z"}, {"count": 1, "pub_date": "2014-06-06T13:24:44Z"}, {"count": 1, "pub_date": "2014-02-12T09:00:48Z"}, {"count": 2, "pub_date": "2015-06-18T00:00:00Z"}, {"count": 1, "pub_date": "2014-10-13T17:37:00Z"}, {"count": 1, "pub_date": "2014-02-03T00:00:00Z"}, {"count": 1, "pub_date": "2014-03-18T12:30:27Z"}, {"count": 1, "pub_date": "2016-06-16T00:00:00Z"}, {"count": 1, "pub_date": "2015-10-17T00:00:00Z"}, {"count": 1, "pub_date": "2015-07-01T19:01:12Z"}, {"count": 1, "pub_date": "2016-07-12T00:00:00Z"}, {"count": 1, "pub_date": "2015-02-27T13:58:44Z"}, {"count": 2, "pub_date": "2016-03-25T00:00:00Z"}, {"count": 2, "pub_date": "2015-02-01T15:43:17Z"}, {"count": 1, "pub_date": "2015-06-12T06:54:34Z"}, {"count": 1, "pub_date": "2014-02-10T09:30:58Z"}, {"count": 1, "pub_date": "2014-10-30T21:42:26Z"}, {"count": 1, "pub_date": "2014-05-13T20:08:11Z"}, {"count": 1, "pub_date": "2015-07-09T00:00:00Z"}, {"count": 1, "pub_date": "2015-05-05T12:11:58Z"}, {"count": 1, "pub_date": "2015-10-24T00:00:00Z"}, {"count": 1, "pub_date": "2014-01-24T14:15:00Z"}, {"count": 1, "pub_date": "2014-05-30T06:30:50Z"}, {"count": 1, "pub_date": "2014-07-02T00:00:00Z"}, {"count": 1, "pub_date": "2014-07-04T00:00:00Z"}, {"count": 1, "pub_date": "2014-06-19T18:27:42Z"}, {"count": 2, "pub_date": "2016-02-03T00:00:00Z"}, {"count": 1, "pub_date": "2016-06-09T00:00:00Z"}, {"count": 1, "pub_date": "2016-10-31T10:13:57+0000"}, {"count": 1, "pub_date": "2015-07-16T00:00:00Z"}, {"count": 1, "pub_date": "2015-07-27T18:18:12Z"}, {"count": 1, "pub_date": "2016-11-30T16:48:21+0000"}, {"count": 1, "pub_date": "2016-06-08T00:00:00Z"}, {"count": 1, "pub_date": "2015-01-14T12:00:48Z"}, {"count": 1, "pub_date": "2016-08-31T04:00:00+0000"}, {"count": 1, "pub_date": "2016-12-09T17:40:45+0000"}, {"count": 1, "pub_date": "2014-05-02T09:54:20Z"}, {"count": 1, "pub_date": "2015-03-20T00:00:00Z"}, {"count": 2, "pub_date": "2015-04-13T19:03:59Z"}, {"count": 2, "pub_date": "2015-06-30T00:00:00Z"}, {"count": 1, "pub_date": "2015-09-28T10:23:29Z"}, {"count": 1, "pub_date": "2014-03-28T11:58:24Z"}, {"count": 2, "pub_date": "2016-05-13T00:00:00Z"}, {"count": 1, "pub_date": "2016-10-03T20:04:44Z"}, {"count": 1, "pub_date": "2015-12-25T00:00:00Z"}, {"count": 1, "pub_date": "2014-06-27T00:00:00Z"}, {"count": 1, "pub_date": "2014-09-29T07:06:25Z"}, {"count": 1, "pub_date": "2015-07-24T11:52:00Z"}, {"count": 1, "pub_date": "2014-04-21T00:00:00Z"}, {"count": 1, "pub_date": "2016-11-11T17:45:12Z"}, {"count": 1, "pub_date": "2014-05-15T00:00:00Z"}, {"count": 1, "pub_date": "2014-08-04T21:41:27Z"}, {"count": 1, "pub_date": "2016-09-02T06:02:55+0000"}, {"count": 1, "pub_date": "2014-12-11T04:43:23Z"}, {"count": 1, "pub_date": "2015-04-23T07:20:02Z"}, {"count": 1, "pub_date": "2014-10-16T00:00:00Z"}, {"count": 1, "pub_date": "2014-09-28T09:00:32Z"}, {"count": 2, "pub_date": "2015-12-08T00:00:00Z"}, {"count": 1, "pub_date": "2017-01-25T23:53:01+0000"}, {"count": 1, "pub_date": "2015-01-01T00:00:00Z"}, {"count": 1, "pub_date": "2016-05-25T00:00:00Z"}, {"count": 1, "pub_date": "2015-03-11T09:00:36Z"}, {"count": 4, "pub_date": "2014-07-24T00:00:00Z"}, {"count": 1, "pub_date": "2015-04-13T00:00:00Z"}, {"count": 1, "pub_date": "2014-05-28T14:56:20Z"}, {"count": 1, "pub_date": "2015-03-05T00:00:00Z"}, {"count": 1, "pub_date": "2014-08-04T15:59:11Z"}, {"count": 1, "pub_date": "2016-06-22T00:00:00Z"}, {"count": 1, "pub_date": "2014-03-13T19:12:09Z"}, {"count": 1, "pub_date": "2014-07-16T00:00:00Z"}, {"count": 1, "pub_date": "2016-07-19T04:00:00Z"}, {"count": 2, "pub_date": "2015-08-28T00:00:00Z"}, {"count": 1, "pub_date": "2016-05-18T00:00:00Z"}, {"count": 1, "pub_date": "2015-09-02T16:19:53Z"}, {"count": 1, "pub_date": "2016-10-06T04:00:00+0000"}, {"count": 1, "pub_date": "2015-02-25T10:00:53Z"}, {"count": 1, "pub_date": "2014-06-11T12:52:03Z"}, {"count": 1, "pub_date": "2017-01-21T14:30:03+0000"}, {"count": 1, "pub_date": "2015-01-06T00:00:00Z"}, {"count": 1, "pub_date": "2017-02-23T12:00:03+0000"}, {"count": 1, "pub_date": "2016-06-02T00:00:00Z"}, {"count": 3, "pub_date": "2015-05-28T00:00:00Z"}, {"count": 3, "pub_date": "2016-02-11T00:00:00Z"}, {"count": 3, "pub_date": "2014-04-17T00:00:00Z"}, {"count": 1, "pub_date": "2016-11-01T15:46:17Z"}, {"count": 1, "pub_date": "2015-07-06T17:22:51Z"}, {"count": 1, "pub_date": "2015-01-14T03:01:37Z"}, {"count": 1, "pub_date": "2014-09-09T17:54:00Z"}, {"count": 2, "pub_date": "2014-05-01T18:08:13Z"}, {"count": 2, "pub_date": "2015-09-24T00:00:00Z"}, {"count": 1, "pub_date": "2015-02-16T00:00:00Z"}, {"count": 2, "pub_date": "2015-08-06T00:00:00Z"}, {"count": 1, "pub_date": "2016-05-07T00:00:00Z"}, {"count": 1, "pub_date": "2015-08-14T15:06:15Z"}, {"count": 1, "pub_date": "2014-12-24T00:00:00Z"}, {"count": 1, "pub_date": "2015-08-06T09:38:56Z"}, {"count": 1, "pub_date": "2015-01-19T00:00:00Z"}, {"count": 3, "pub_date": "2014-06-27T16:53:05Z"}, {"count": 1, "pub_date": "2014-09-26T13:41:39Z"}]